Workbook

Sheet README
A1: FIRE 統合要件書 v3.1 — 全開発TODO管理表
A3: 作成日 | B3: 2026-04-21
A4: 対象要件書 | B4: FIRE 統合要件書 v3.1（製本版）
A5: 開発環境 | B5: 初期: Windows PC(全ロジック開発) / Mac mini M4 Pro 到着後: 常駐運用基盤へ移行
A6: 管理方針 | B6: Git + Obsidian + .md で開発進捗を可視化、タスク完了時に必ずクローズ
A8: ■ シート構成
A9: README | B9: 本シート（凡例・使い方）
A10: TODO_Master | B10: 全開発タスク一覧（メインシート）
A11: Phase_Summary | B11: フェーズ別サマリー（進捗集計）
A12: Agent_Checklist | B12: 10エージェント別の実装チェックリスト
A13: Stage_Gate | B13: Stage 0→4 昇格ゲートチェックリスト
A14: Roadmap | B14: M-3 〜 M+3 立ち上げロードマップ
A15: Risk_Holes | B15: 穴1〜11（要件書で特定された落とし穴）対策チェック
A17: ■ ステータス定義
A18: 未着手 | B18: まだ着手していない
A19: 設計中 | B19: 設計・検討フェーズ
A20: 実装中 | B20: コード実装中
A21: 検証中 | B21: テスト・Simulation検証中
A22: レビュー待ち | B22: ユーザー承認待ち
A23: 完了 | B23: タスククローズ済み
A24: 凍結 | B24: 一時保留
A26: ■ 優先度定義
A27: 最優先 | B27: これが無いと次に進めない（Pattern Store、Runtime骨組み等）
A28: 高 | B28: 主戦略・本番運用に必須
A29: 中 | B29: 運用品質向上に必要
A30: 低 | B30: 後回し可（後から拡張）
A32: ■ 開発着手順の最重要前提（要件書15章・23章より）
A33: 1 | B33: Pattern Store / Feature Store / Runtime / Simulation の骨組みを最優先で作成
A34: 2 | B34: リアルタイム Paper Live 環境 + LINE通知基盤を構築
A35: 3 | B35: 実弾執行基盤（証券API連携）は後回しで着手
A36: 4 | B36: 各エージェントのプロンプトファイルを整備
A38: ■ 使い方
A39: 1 | B39: TODO_Master シートで各タスクのステータスを更新
A40: 2 | B40: 完了したらステータスを「完了」に変更し、完了日を入力
A41: 3 | B41: Phase_Summary で進捗を自動集計（SUMIFS/COUNTIFS）
A42: 4 | B42: GitとObsidianに対応する.mdファイルを必ず作成し、本表のタスクIDを記載
A45: ■ 要件トレーサビリティマトリクス (RTM)
A46: RTM_要件カバレッジ | B46: 要件書全要件を要件ID(R-章-連番)で採番し、対応タスクIDを紐付け。赤=未カバー、黄=1件紐付け、緑=2件以上
A47: RTM_章別サマリー | B47: 章別の要件数・カバー済・未カバー・カバレッジ率を自動集計。未カバーが1件でもある章を黄色ハイライト
A49: ■ 要件抜け漏れ確認の正式な場所
A50: 1 | B50: 『RTM_章別サマリー』で黄色ハイライトされた章を確認
A51: 2 | B51: 該当章に移動し、『RTM_要件カバレッジ』で赤ハイライトの要件(=タスク未紐付け)を特定
A52: 3 | B52: 赤要件をタスク化するか、対応不要な理由を明記する
A53: 4 | B53: 新規タスクをTODO_Masterに追加後、RTMの対応タスクID列を更新
A56: ■ Mac mini 到着待ち対応(v3で追加)
A57: 開発・運用フェーズ計画 | B57: Mac到着待ち期間の開発順序を整理。D1-D7はWindowsで完結、D8でMac移行。
A59: ■ Mac mini到着前後の方針
A60: 到着前 | B60: WindowsでD1-D7(基盤/Store/Sim/エージェント/通知/Dashboard/縮退運転/擬似Paper Live)を進める
A61: 到着後 | B61: D8(F002→F003→F013→F016)を短期集中で実施、Mac常駐化しM-3スタート
A62: 遅延時 | B62: Windowsでの開発完成度を高める時間が増える。D1-D7のタスク消化率を上げる

Sheet TODO_Master
A1: ID | B1: フェーズ | C1: カテゴリ | D1: 要件書章 | E1: タスク名 | F1: 詳細 | G1: 優先度 | H1: 依存 | I1: 担当 | J1: 想定工数(日) | K1: ステータス | L1: 着手日 | M1: 完了日 | N1: 成果物 | O1: 備考
A2: F001 | B2: P0: 基盤・環境構築 | C2: 移行準備 | D2: - | E2: Windows資産のZIP化・クラウドアップロード(Mac到着前) | F2: Windows PCで fire-vault をZIP化し、Google Drive等にアップロード。FIRE_開発TODO_v7.xlsx、要件書PDF原本、引き継ぎコンテキスト.md も一緒にアップ。Mac mini到着時に即ダウンロードできる状態にする。 | G2: 最優先 | I2: Fujiwara | J2: 0.2 | K2: 完了 | N2: Google Drive上のfire-vault_backup.zip + 関連ファイル一式 | O2: Mac mini到着前に完了させておく。Windows_to_Mac_移行手順.md 参照
A3: F019 | B3: P0: 基盤・環境構築 | C3: アカウント | D3: - | E3: Claude 個人アカウント契約(Pro or Max) | F3: FIRE開発専用のClaude個人アカウントを契約(StudioZ業務用とは分離)。推奨はClaude Pro($20/月)またはMaxプラン。Claude Code利用のため2FA必須。契約後、新アカウントで引き継ぎコンテキスト.mdを投入してFIRE開発を継続。 | G3: 最優先 | H3: F001 | I3: Fujiwara | J3: 0.2 | K3: 完了 | N3: 新Claudeアカウント(個人用・Pro/Max契約済み) | O3: Claude Code の長時間実行・大容量コンテキストに対応するため有料プラン推奨
A4: F002 | B4: P0: 基盤・環境構築 | C4: 環境 | D4: 16 | E4: Mac mini M4 Pro 受領・初期設定 | F4: システム設定: スリープしない/自動再起動/自動ログイン/ファイアウォール/画面共有/SSH/Tailscale。要件書16章。 | G4: 最優先 | H4: F019 | I4: Fujiwara | J4: Fujiwara | K4: 完了 | N4: Mac mini運用環境 | O4: Claude個人アカウント契約(F019)完了後、Mac受領時に着手
A5: F003 | B5: P0: 基盤・環境構築 | C5: 環境 | D5: 16 | E5: Mac mini 開発環境セットアップ | F5: Homebrew / Python@3.12 / Node.js LTS / Git / Obsidian / VS Code + 拡張をbrewとApp Storeで一括導入。.zshrc に環境変数設定。 | G5: 最優先 | H5: F002 | I5: Fujiwara | J5: Fujiwara | K5: 完了 | N5: Mac環境 | O5: Windows で決めたツール構成をMac版で再現
A6: F016 | B6: P0: 基盤・環境構築 | C6: 移行 | D6: - | E6: Windows資産のMac mini移行 | F6: Obsidian Vault(fire-vault)/要件書39章.md/タスク運用ルール.md/Google Sheetsリンクを iCloud・Dropbox・GitHub経由でMacに展開。GitHub(BlueFire7777)の鍵登録。 | G6: 最優先 | H6: F001,F003 | I6: 両方 | J6: Fujiwara | K6: 完了 | N6: docs/migration_to_mac.md | O6: Windows側で作成したZIP(F001)を Mac に展開。F003 の Mac 開発環境セットアップ完了後
A7: F017 | B7: P0: 基盤・環境構築 | C7: ドキュメント | D7: - | E7: Claudeアカウント引き継ぎ・新ランタイム確認 | F7: 新Claude個人アカウント(F019)でFIREプロジェクトコンテキストを引き継ぎ、CLAUDE.mdと要件書を認識させる。Windows資産(F016)がMac上で使える状態で動作確認。 | G7: 最優先 | H7: F019,F016 | I7: Fujiwara | J7: 0.5 | K7: 完了 | N7: 新アカウントでのclaude動作確認 | O7: 新Claudeアカウントでの継続運用の起点
A8: F018 | B8: P0: 基盤・環境構築 | C8: 環境 | D8: 16 | E8: Mac .zshrc プロファイル設定 | F8: $FIRE_HOME / $FIRE_VAULT / $CLAUDE_CODE_EFFORT_LEVEL / $FIRE_PLATFORM=mac 等の環境変数と、fire / firevault / py312 等のエイリアス・関数を.zshrcに設定。 | G8: 最優先 | H8: F003 | I8: Fujiwara | J8: 0.3 | K8: 完了 | N8: ~/.zshrc | O8: Windows PowerShellプロファイルのMac版
A9: F235 | B9: P0: 基盤・環境構築 | C9: 証券会社設定 | D9: 14 | E9: 楽天証券 約定通知メール設定 | F9: 楽天証券ログイン → 設定・変更 → お知らせメール設定 → 注文約定通知 ON。M+2 以降に Gmail API で自動取込するための前提設定。Fujiwara さん自身の作業。 | G9: 最優先 | I9: Fujiwara | J9: 0.1 | K9: 完了 | N9: 楽天証券の約定通知メール配信設定 | O9: v3.3 新規。M+2 以降の Gmail API 自動取込の前提
A10: F242 | B10: P0: 基盤・環境構築 | C10: 基盤 | D10: 23 | E10: OpenClaw セットアップ(Mac mini 常駐基盤) | F10: Mac mini M4 Pro に OpenClaw をインストールし、常駐・スケジュール・並列実行・自動復旧・セッション永続化の基盤を確立。ハートビートと再起動テスト。Anthropic API キー設定。 | G10: 最優先 | H10: F003 | I10: Claude | J10: 3 | K10: 完了 | N10: OpenClaw on Mac mini 稼働状態 | O10: v3.3 の核心。FIRE 専用ランナー自作を廃止して OpenClaw 採用
A11: F004 | B11: P0: 基盤・環境構築 | C11: リポジトリ | D11: 15 | E11: Gitリポジトリ初期化 | F11: fireリポジトリ作成、README.md/CLAUDE.md/.gitignore/requirements.txt/package.json作成。ブランチ戦略(main/dev/feature)定義。 | G11: 最優先 | H11: F001 | I11: 両方 | J11: 0.5 | K11: 完了 | N11: github.com/xxx/fire
A12: F005 | B12: P0: 基盤・環境構築 | C12: ドキュメント | D12: 15 | E12: CLAUDE.md 初稿作成 | F12: Claude Codeへの実装指示書。要件書の決定事項を削らず記載。崩してはならない前提リスト。 | G12: 最優先 | H12: F004 | I12: Claude | J12: 0.5 | K12: 完了 | N12: CLAUDE.md
A13: F006 | B13: P0: 基盤・環境構築 | C13: ドキュメント | D13: 15 | E13: README.md 初稿作成 | F13: プロジェクト概要、セットアップ手順、ディレクトリ構造、開発フロー記載。 | G13: 最優先 | H13: F004 | I13: Claude | J13: 0.5 | K13: 完了 | N13: README.md
A14: F007 | B14: P0: 基盤・環境構築 | C14: ドキュメント | D14: - | E14: Obsidian Vault 構築 | F14: 開発ログ/設計メモ/日次レビュー用のVault作成。docs/配下と連携。タスクIDリンク運用。 | G14: 最優先 | H14: F004 | I14: Fujiwara | J14: 0.5 | K14: 完了 | N14: Obsidian Vault
A15: F008 | B15: P0: 基盤・環境構築 | C15: ディレクトリ | D15: - | E15: プロジェクトディレクトリ構造設計 | F15: agents/ runtime/ patterns/ features/ simulation/ dashboard/ notifications/ broker/ data/ logs/ docs/ tests/ scripts/ | G15: 最優先 | H15: F004 | I15: Claude | J15: 0.5 | K15: 完了 | N15: ディレクトリ構造
A16: F011 | B16: P0: 基盤・環境構築 | C16: DB | D16: - | E16: ローカルDB選定・初期化 | F16: Pattern/Feature/Live Research Log用。SQLite or DuckDB or PostgreSQL選定。スキーマ設計。 | G16: 最優先 | H16: F008 | I16: Claude | J16: 1 | K16: 完了 | N16: db/schema.sql
A17: F012 | B17: P0: 基盤・環境構築 | C17: スケジューラ | D17: 23 | E17: FIRE Runner骨組み | F17: メインオーケストレーター。エージェント起動/停止/スケジュール管理。時間帯別処理起動。Windows/Mac両対応で実装。 | G17: 最優先 | H17: F010 | I17: Claude | J17: 2 | K17: 完了 | N17: runtime/main.py | O17: OS非依存で実装。launchd固有部分はF013で追加
A18: F013 | B18: P0: 基盤・環境構築 | C18: launchd | D18: 16 | E18: Mac mini launchd常駐自動起動設定 | F18: ~/Library/LaunchAgents/com.fire.runtime.plist作成、launchctl load、動作確認。FIRE Runtime常駐基盤の完成。 | G18: 最優先 | H18: F003,F012 | I18: Fujiwara | J18: Fujiwara | K18: 完了 | N18: com.fire.runtime.plist | O18: 要件書16章。常駐化により以降のPaper Live本格稼働が可能に
A19: F009 | B19: P0: 基盤・環境構築 | C19: 設定 | D19: 16 | E19: 環境変数管理基盤 | F19: .env設計、RAKUTEN_API_KEY/LINE_CHANNEL_TOKEN/NEWS_API_KEY/TDNET_API_KEY等。.env.example整備。秘匿情報のgit除外。 | G19: 高 | H19: F004 | I19: Claude | J19: 0.5 | K19: 完了 | N19: .env, .env.example
A20: F010 | B20: P0: 基盤・環境構築 | C20: ロギング | D20: - | E20: 共通ロギング基盤 | F20: logs/配下に構造化ログ(JSON)。レベル分け、ローテーション、監査用の永続化。 | G20: 高 | H20: F008 | I20: Claude | J20: 1 | K20: 完了 | N20: utils/logger.py
A21: F020 | B21: P1: Pattern/Feature Store | C21: データ基盤 | D21: 21,36 | E21: Feature Store スキーマ設計 | F21: 6系統特徴量(材料/地合い/出来高/値動き/執行品質/時間帯)の全カラム定義。時系列/スナップショット管理。 | G21: 最優先 | H21: F011 | I21: Claude | J21: 2 | K21: 完了 | N21: features/schema.md
A22: F027 | B22: P1: Pattern/Feature Store | C22: Store | D22: 11,21,37 | E22: Pattern Store 4階層構造実装 | F22: Layer1: Pattern Archive / Layer2: Valid Library / Layer3: Active Priority Set / Layer4: Death Note・Rehab。 | G22: 最優先 | H22: F011,F020 | I22: Claude | J22: 3 | K22: 完了 | N22: patterns/store.py
A23: F028 | B23: P1: Pattern/Feature Store | C23: Store | D23: 21,37 | E23: パターン7状態管理 | F23: candidate/paper_validating/approved_active/watchlist/frozen/death_note/rehab の遷移ルール実装。 | G23: 最優先 | H23: F027 | I23: Claude | J23: 1.5 | K23: 完了 | N23: patterns/state_machine.py
A24: F031 | B24: P1: Pattern/Feature Store | C24: 検索 | D24: 11,21,26 | E24: 類似局面検索エンジン | F24: Feature Storeから現在局面と過去局面の類似度計算。重み付け(材料30/地合い20/流動性20/値動き20/執行10)。 | G24: 最優先 | H24: F020,F027 | I24: Claude | J24: 3 | K24: 完了 | N24: patterns/similarity.py
A25: F032 | B25: P1: Pattern/Feature Store | C25: スコアリング | D25: 11,26 | E25: 再現性スコア合成エンジン | F25: 類似度+類似件数+勝率+平均RR+期待値+レジーム適合+直近有効性+執行品質+リスク管理適合 の合成。 | G25: 最優先 | H25: F031 | I25: Claude | J25: 2 | K25: 完了 | N25: patterns/repro_score.py
A26: F180 | B26: P1: Pattern/Feature Store | C26: ラベル | D26: 29 | E26: 成功/失敗ラベル4分類 | F26: Success/Failure/Timeout/Invalid。target_holding_window内で損切より先に利確1到達=Success。 | G26: 最優先 | H26: F020 | I26: Claude | J26: 1.5 | K26: 完了 | N26: labels/classifier.py
A27: F200 | B27: P1: Pattern/Feature Store | C27: 戦略 | D27: 3,25 | E27: 3レーン戦略構造 | F27: Primary(材料初動80%+主役テーマ値嵩)/Secondary(押し目再加速等 20%/M+2までPaper並走)/Research(準スキャル等)。 | G27: 最優先 | H27: F111 | I27: Claude | J27: 2 | K27: 完了 | N27: strategies/lanes.py
A28: F021 | B28: P1: Pattern/Feature Store | C28: データ取得 | D28: 36 | E28: 材料特徴量収集エンジン | F28: material_type/freshness/strength_score/multi_material_flag/earnings_related_flag/shareholder_return_flag。 | G28: 高 | H28: F020 | I28: Claude | J28: 2 | K28: 完了 | N28: features/material.py | O28: TDnet/IR/NewsAPI連携は後続
A29: F022 | B29: P1: Pattern/Feature Store | C29: データ取得 | D29: 36 | E29: 地合い特徴量収集エンジン | F29: nikkei/topix_direction、sector_strength_rank、theme_strength_rank、market_regime分類、usd_jpy、overnight_us。 | G29: 高 | H29: F020 | I29: Claude | J29: 2 | K29: 完了 | N29: features/regime.py
A30: F023 | B30: P1: Pattern/Feature Store | C30: データ取得 | D30: 36 | E30: 出来高/流動性特徴量エンジン | F30: volume_ratio/turnover/liquidity_score/spread_estimate/high_price_stock_flag/board_thickness_score。 | G30: 高 | H30: F020 | I30: Claude | J30: 1.5 | K30: 完了 | N30: features/liquidity.py
A31: F024 | B31: P1: Pattern/Feature Store | C31: データ取得 | D31: 36 | E31: 値動き/テクニカル特徴量エンジン | F31: gap_pct/intraday_range/breakout/pullback/vwap_position/ma_alignment/RS/price_action_pattern/S&R距離。 | G31: 高 | H31: F020 | I31: Claude | J31: 2 | K31: 完了 | N31: features/technical.py
A32: F025 | B32: P1: Pattern/Feature Store | C32: データ取得 | D32: 36 | E32: 執行品質特徴量エンジン | F32: entry/stop_slippage_estimate、partial_fill_risk、fill_quality_score、forced_close_risk_score。 | G32: 高 | H32: F020 | I32: Claude | J32: 1.5 | K32: 完了 | N32: features/execution.py
A33: F026 | B33: P1: Pattern/Feature Store | C33: データ取得 | D33: 36 | E33: 時間帯特徴量エンジン | F33: session_phase/minutes_from_open/minutes_to_force_close/material_to_entry_lag_minutes。 | G33: 高 | H33: F020 | I33: Claude | J33: 1 | K33: 完了 | N33: features/time.py
A34: F029 | B34: P1: Pattern/Feature Store | C34: Store | D34: 37 | E34: パターン格付け(S〜X)実装 | F34: S/A/B/C/D/X のランク付けと自動判定ロジック。再現性スコア/期待値/類似件数ベース。 | G34: 高 | H34: F028 | I34: Claude | J34: 1 | K34: 完了 | N34: patterns/ranking.py
A35: F030 | B35: P1: Pattern/Feature Store | C35: Store | D35: 21,31,37 | E35: pattern_id / 命名規則 / バージョン管理 | F35: [material]-[regime]-[price_action]-[time]-[liquidity] 形式。parent_pattern_id、change_reason必須。 | G35: 高 | H35: F027 | I35: Claude | J35: 1 | K35: 完了 | N35: patterns/naming.py
A36: F033 | B36: P1: Pattern/Feature Store | C36: DEATH NOTE | D36: 21 | E36: DEATH NOTE 3段階判定 | F36: Step1(5回で4敗)→要警戒 / Step2(10回勝率30%未満)→凍結候補 / Step3(20回期待値マイナス)→DEATH NOTE。 | G36: 高 | H36: F028 | I36: Claude | J36: 1 | K36: 完了 | N36: patterns/death_note.py | O36: 単純連敗即死禁止
A37: F035 | B37: P1: Pattern/Feature Store | C37: Agent | D37: 21 | E37: Pattern Research Agent | F37: パターン研究責任者。過去/リアルタイムからの発見・定義・更新提案。自動反映禁止。 | G37: 高 | H37: F031,F032 | I37: Claude | J37: 3 | K37: 完了 | N37: agents/pattern_research.py
A38: F036 | B38: P1: Pattern/Feature Store | C38: ログ | D38: 21 | E38: Live Research Log 実装 | F38: リアルタイム観測ログ。候補/類似パターン/実成績/最大含み益/最大逆行/約定品質/地合い保存。 | G38: 高 | H38: F035 | I38: Claude | J38: 1.5 | K38: 完了 | N38: patterns/live_log.py
A39: F038 | B39: P1: Pattern/Feature Store | C39: 承認フロー | D39: 21 | E39: パターン採用承認フロー | F39: candidate→Paper/Sim検証→Evaluation評価→ユーザー承認→Library登録。凍結/DN/REHABも承認制。 | G39: 高 | H39: F035 | I39: Claude | J39: 1 | K39: 未着手 | N39: patterns/approval.py
A40: F181 | B40: P1: Pattern/Feature Store | C40: ラベル | D40: 29 | E40: target_holding_window パターン別管理 | F40: 材料初動10-30分/主役テーマ15-45分/準スキャル3-10分。 | G40: 高 | H40: F180 | I40: Claude | J40: 0.5 | K40: 未着手 | N40: labels/windows.py
A41: F182 | B41: P1: Pattern/Feature Store | C41: ラベル | D41: 29 | E41: 補助メトリクス保存 | F41: mfe_pct/mae_pct/time_to_mfe/mae/tp/sl/pnl_at_timeout/close/fill_quality_score。 | G41: 高 | H41: F180 | I41: Claude | J41: 1 | K41: 未着手 | N41: labels/metrics.py
A42: F183 | B42: P1: Pattern/Feature Store | C42: ラベル | D42: 29 | E42: Pattern Library採用最重要指標 | F42: success_rate/failure_rate/timeout_rate/expectancy/avg_rr/mae/mfe/regime別/fill_adjusted_expectancy。 | G42: 高 | H42: F182 | I42: Claude | J42: 1 | K42: 未着手 | N42: labels/adoption_metrics.py | O42: 勝率だけで採用禁止
A43: F201 | B43: P1: Pattern/Feature Store | C43: 戦略 | D43: 25 | E43: 頻度監視(0-3件/日、5-10件/週) | F43: 2週間連続頻度不足をEvaluationが検知。フィルター厳しすぎ点検。 | G43: 高 | H43: F119 | I43: Claude | J43: 0.5 | K43: 未着手 | N43: strategies/frequency.py
A44: F202 | B44: P1: Pattern/Feature Store | C44: 戦略 | D44: 25 | E44: 決算シーズン特別ルール | F44: 材料母集団広め/実行候補1-3件固定/フィルター厳格化/優先・除外条件明文化。 | G44: 高 | H44: F200 | I44: Claude | J44: 1 | K44: 未着手 | N44: strategies/earnings_season.py
A45: F034 | B45: P1: Pattern/Feature Store | C45: REHAB | D45: 21 | E45: REHAB Queue 管理 | F45: 凍結/DEATH NOTE復帰候補の保管。決算期限定/強地合い限定/セクター限定/執行改善後の再挑戦。 | G45: 中 | H45: F033 | I45: Claude | J45: 1 | K45: 未着手 | N45: patterns/rehab.py | O45: 自動復帰禁止
A46: F037 | B46: P1: Pattern/Feature Store | C46: 品質管理 | D46: 31,37 | E46: パターン重複統合ルール | F46: コア特徴量重複度の閾値判定。親子関係化/alias扱い/統合の運用。週次棚卸し。 | G46: 中 | H46: F030 | I46: Claude | J46: 1 | K46: 未着手 | N46: patterns/dedup.py
A47: F040 | B47: P2: Simulation/Backtest | C47: Simulation | D47: 19 | E47: Backtest Mode (Stage 0) | F47: 過去データでのルールベース検証。戦略有効性/候補抽出/エッジ別成績/損益傾向。 | G47: 最優先 | H47: F020,F031 | I47: Claude | J47: 3 | K47: 未着手 | N47: simulation/backtest.py
A48: F041 | B48: P2: Simulation/Backtest | C48: Simulation | D48: 19 | E48: Replay Simulation Mode (Stage 1) | F48: 過去特定日の時系列再生。当時利用可能情報のみ使用し後知恵バイアス排除。 | G48: 最優先 | H48: F040 | I48: Claude | J48: 3 | K48: 未着手 | N48: simulation/replay.py
A49: F043 | B49: P2: Simulation/Backtest | C49: 約定モデル | D49: 19 | E49: 現実寄り約定モデル (B) | F49: スプレッド/価格乖離/約定遅延/部分約定考慮。標準simulation精度確認用。 | G49: 最優先 | H49: F042 | I49: Claude | J49: 2 | K49: 未着手 | N49: simulation/fill_realistic.py
A50: F044 | B50: P2: Simulation/Backtest | C50: 約定モデル | D50: 19 | E50: 厳しめ約定モデル (C) | F50: +2ティック/値嵩株1.5倍/寄り直後1.5倍。楽観バイアス検出用。指値未約定リスクもモデル化。 | G50: 最優先 | H50: F043 | I50: Claude | J50: 2 | K50: 未着手 | N50: simulation/fill_strict.py
A51: F045 | B51: P2: Simulation/Backtest | C51: 高速リプレイ | D51: 12,19,32 | E51: 過去データ高速リプレイ並列実行 | F51: Mac mini常時稼働を活かしたカレンダー日数短縮。20営業日50トレード基準を過去データでクリア可能に。 | G51: 最優先 | H51: F041 | I51: Claude | J51: 3 | K51: 未着手 | N51: simulation/parallel_replay.py | O51: M-3期の爆速蓄積用
A52: F042 | B52: P2: Simulation/Backtest | C52: 約定モデル | D52: 19 | E52: 理想約定モデル (A) | F52: シグナル価格でそのまま約定。最楽観。戦略純粋方向性確認用。 | G52: 高 | H52: F040 | I52: Claude | J52: 1 | K52: 未着手 | N52: simulation/fill_ideal.py
A53: F046 | B53: P2: Simulation/Backtest | C53: 精度指標 | D53: 19 | E53: Simulation Accuracy 指標算出 | F53: 仮想vs実現的価格の比較。仮想約定率/利確到達率/損切率/強制クローズ成功率。 | G53: 高 | H53: F043 | I53: Claude | J53: 1.5 | K53: 未着手 | N53: simulation/accuracy.py
A54: F047 | B54: P2: Simulation/Backtest | C54: 精度指標 | D54: 19 | E54: Optimistic Bias / Realistic Fill Score | F54: Simulation Confidence Score / Optimistic Bias Score / Realistic Fill Score 算出。 | G54: 高 | H54: F046 | I54: Claude | J54: 1 | K54: 未着手 | N54: simulation/bias_score.py
A55: F050 | B55: P3: Paper Live | C55: Runtime | D55: 19,23 | E55: Paper Live Mode (Stage 2) 本体 | F55: リアルタイム相場で仮想売買。朝レポート/候補抽出/厳選/条件監視/仮想建玉/仮想余力。 | G55: 最優先 | H55: F043,F012 | I55: Claude | J55: 4 | K55: 未着手 | N55: simulation/paper_live.py
A56: F051 | B56: P3: Paper Live | C56: 仮想管理 | D56: 19 | E56: 仮想建玉/平均建値/評価損益/実現損益/余力管理 | F56: 仮想ロット消費状況/仮想停止状態管理。新規/利確/損切/強制クローズ/注文取消/失効の全カバー。 | G56: 最優先 | H56: F050 | I56: Claude | J56: 2 | K56: 未着手 | N56: simulation/virtual_book.py
A57: F052 | B57: P3: Paper Live | C57: 厳しめモデル統合 | D57: 19 | E57: Paper Live厳しめ約定モデル標準化 | F57: +2ティック/値嵩株1.5倍/寄り直後1.5倍をPaper Liveの標準約定モデルとする。 | G57: 最優先 | H57: F044,F050 | I57: Claude | J57: 1 | K57: 未着手 | N57: simulation/paper_fill.py
A58: F053 | B58: P3: Paper Live | C58: 検証 | D58: 32 | E58: Paper Live→Semi Auto 昇格基準実装 | F58: 20営業日 or 50トレード / 期待値プラス / DD上限 / 強制クローズ100% / 停止機能正常 を自動判定。 | G58: 高 | H58: F050,F046 | I58: Claude | J58: 1.5 | K58: 未着手 | N58: simulation/promotion_check.py
A59: F236 | B59: P4: LINE/通知基盤 | C59: 通知 | D59: 06,38 | E59: LINE 緊急ポジション整理部屋 5段階アラート実装 | F59: LINE 通知 5部屋の 1つとして 🚨 緊急ポジション整理部屋を新設。14:45/14:55/15:05/15:10/15:15 の段階アラート。独立性担保のため macOS 標準 Cron から起動(OpenClaw 障害時も稼働継続)。建玉残 0 件なら通知スキップ。 | G59: 最優先 | H59: F242 | I59: Claude | J59: 2 | K59: 未着手 | N59: 緊急ポジション整理部屋稼働 | O59: v3.3 新規。v3.2 の Playwright 自動クローズを置換
A60: F060 | B60: P4: LINE/通知基盤 | C60: API | D60: 6 | E60: LINE Messaging API連携基盤 | F60: LINE Channel Token管理、送信関数、エラーハンドリング、リトライ。 | G60: 最優先 | H60: F009 | I60: Claude | J60: 1.5 | K60: 未着手 | N60: notifications/line_client.py
A61: F061 | B61: P4: LINE/通知基盤 | C61: 通知設計 | D61: 6 | E61: LINE通知4部屋分離 | F61: エントリー/執行損益/レポート/システム警告。必須項目の完成形化。 | G61: 最優先 | H61: F060 | I61: Claude | J61: 1 | K61: 未着手 | N61: notifications/rooms.py
A62: F111 | B62: P4: LINE/通知基盤 | C62: Agent | D62: 4,7,8 | E62: Daytrade Selection Agent | F62: デイトレ候補抽出・厳選(1〜3銘柄)。スコア付与(地合い15/テーマ15/流動性20/値動き20/値嵩10/RR10/補助10)。 | G62: 最優先 | H62: F031,F032 | I62: Claude | J62: 3 | K62: 未着手 | N62: agents/daytrade_select.py
A63: F115 | B63: P4: LINE/通知基盤 | C63: Agent | D63: 4,5 | E63: Trade Decision Agent | F63: エントリー/利確/損切/株数提案。ロット計算(許容損失÷(エントリー-損切))、100株丸め。注文案生成。 | G63: 最優先 | H63: F111 | I63: Claude | J63: 3 | K63: 未着手 | N63: agents/trade_decision.py
A64: F116 | B64: P4: LINE/通知基盤 | C64: Agent | D64: 4,6 | E64: Monitoring & Alert Agent | F64: 価格到達監視。LINE通知発火。特買い/特売り検知。Windows開発段階ではPaper Live専用、本番はMac miniで常駐。 | G64: 最優先 | H64: F060,F100 | I64: Claude | J64: 2 | K64: 未着手 | N64: agents/monitoring.py | O64: OS非依存ロジック。Windowsでも試験可
A65: F119 | B65: P4: LINE/通知基盤 | C65: Agent | D65: 4,13 | E65: Evaluation Agent | F65: 候補抽出/執行/リスク管理/システム/エッジ別を評価。改善提案書作成。自動反映禁止・承認制。 | G65: 最優先 | H65: F035 | I65: Claude | J65: 4 | K65: 未着手 | N65: agents/evaluation.py
A66: F130 | B66: P4: LINE/通知基盤 | C66: リスク | D66: 5 | E66: 許容損失 準攻撃型実装 | F66: デイトレ通常0.4%/強気0.5%/弱気0.25-0.3%。スイング通常0.6%/強気0.8%。長期1.2%(分割買い)。 | G66: 最優先 | H66: F115 | I66: Claude | J66: 1 | K66: 未着手 | N66: risk/allowable_loss.py
A67: F131 | B67: P4: LINE/通知基盤 | C67: リスク | D67: 5,39 | E67: M=0 初月半減ルール | F67: デイトレ0.2%/スイング0.3%開始。M+1で0.3%、M+2〜で要件書通り0.4%復帰。 | G67: 最優先 | H67: F130 | I67: Claude | J67: 0.5 | K67: 未着手 | N67: risk/m0_scaling.py
A68: F132 | B68: P4: LINE/通知基盤 | C68: リスク | D68: 5 | E68: 日次・週次損失制御 | F68: 日次-1.2%新規停止/-1.8%終了。週次-3.0%守備/-4.0%大幅制限/-5.0%原則停止。 | G68: 最優先 | H68: F130 | I68: Claude | J68: 1 | K68: 未着手 | N68: risk/daily_weekly_stop.py
A69: F133 | B69: P4: LINE/通知基盤 | C69: リスク | D69: 5,9 | E69: 強制クローズ独立プロセス | F69: 別ファイル+Cron起動のフェイルセーフ。14:45新規禁止/15:10完了期限。15:08強制モード。 | G69: 最優先 | H69: F132 | I69: Claude | J69: 2 | K69: 未着手 | N69: risk/force_close.py | O69: 独立プロセスで実装
A70: F140 | B70: P4: LINE/通知基盤 | C70: 執行 | D70: 17 | E70: Execution Quality Gate 実装 | F70: 板厚/スプレッド/出来高/部分約定リスク/値飛びリスク/値嵩滑りやすさ判定。スコア高でもNGなら見送り。 | G70: 最優先 | H70: F025,F115 | I70: Claude | J70: 2 | K70: 未着手 | N70: execution/quality_gate.py
A71: F141 | B71: P4: LINE/通知基盤 | C71: 執行 | D71: 17 | E71: ハイブリッド執行方針 | F71: Sランク材料=逆指値→成行ブレイク狙い。通常=指値主体。例外条件明文化。 | G71: 最優先 | H71: F140 | I71: Claude | J71: 1 | K71: 未着手 | N71: execution/hybrid.py
A72: F144 | B72: P4: LINE/通知基盤 | C72: 執行 | D72: 12,17 | E72: 執行品質3段階アラート+自己キャリブレーション | F72: 注意(直近5・2.0倍超/LINE警告)/警戒(直近10・2.5倍超/リスク半減)/停止(直近10・3.0倍超/即時停止)。30日後は実測ベース。 | G72: 最優先 | H72: F140 | I72: Claude | J72: 2 | K72: 未着手 | N72: execution/slippage_monitor.py
A73: F211 | B73: P4: LINE/通知基盤 | C73: 目標 | D73: 27 | E73: 目標圧力と運用規律の分離 | F73: 乖離を理由にロット/基準/準主戦略格上げ/停止条件緩和を自動で行わない。相場条件でリスク量決定。 | G73: 最優先 | H73: F130,F210 | I73: Claude | J73: 0.5 | K73: 未着手 | N73: goal/discipline.py
A74: F237 | B74: P4: LINE/通知基盤 | C74: 障害対応 | D74: 22,23 | E74: OpenClaw 障害時縮退運転機構 | F74: OpenClaw が停止した場合の対応:(1) macOS Cron がハートビート不在を1分以内に検知、(2) 自動で Fujiwara さんに LINE で「FIRE 縮退モード起動」通知、(3) 緊急ポジション整理アラートは macOS Cron で独立稼働継続、(4) 復旧後に想定建玉と楽天証券実態を再整合。 | G74: 高 | H74: F242,F236 | I74: Claude | J74: 2 | K74: 未着手 | N74: 縮退運転機構 + ハートビート検知スクリプト | O74: v3.3 新規
A75: F238 | B75: P4: LINE/通知基盤 | C75: 通知 | D75: 06,14 | E75: LINE 約定手動報告パーサー(初期運用用) | F75: M=0〜M+1 の期間、Fujiwara さんが LINE で約定報告(シグナルID・約定価格・株数・時刻・部分約定の有無)した内容をパースして FIRE の建玉DB に記録。M+2 以降は Gmail API 経由に移行するが、補助手段として継続運用。 | G75: 高 | H75: F242 | I75: Claude | J75: 1.5 | K75: 未着手 | N75: LINE 約定報告パーサー | O75: v3.3 新規。M=0 時点で必須
A76: F062 | B76: P4: LINE/通知基盤 | C76: テンプレ | D76: 6 | E76: 発注完成形テンプレート実装 | F76: 銘柄/売買/行動/価格/株数/逆指値/利確(分割)/損切/有効期限/無効条件/一言戦略。 | G76: 高 | H76: F061 | I76: Claude | J76: 1 | K76: 未着手 | N76: notifications/templates.py | O76: 200株:利確2段/100株:1段
A77: F063 | B77: P4: LINE/通知基盤 | C77: 通知階層 | D77: 33 | E77: 4階層通知(緊急/重要/情報/参考) | F77: 即時LINE/朝夕レポート集約/Dashboard閲覧時のみ、の出し分け。 | G77: 高 | H77: F061 | I77: Claude | J77: 1 | K77: 未着手 | N77: notifications/levels.py
A78: F064 | B78: P4: LINE/通知基盤 | C78: 双方向 | D78: 38 | E78: LINEコマンド受信(停止/モード変更/承認) | F78: Webhook受信、コマンドパース、稼働ON/OFF/モード切替/緊急停止/承認却下。 | G78: 高 | H78: F060 | I78: Claude | J78: 2 | K78: 未着手 | N78: notifications/webhook.py
A79: F070 | B79: P4: LINE/通知基盤 | C79: レポート | D79: 6 | E79: 朝レポート生成 (08:30送信) | F79: NotebookLM風。3行要約/世界情勢/日米市場/ニュース洞察/高確率5件/偏り/今日やること。PDF生成。 | G79: 高 | H79: F061,F021,F022 | I79: Claude | J79: 3 | K79: 未着手 | N79: reports/morning.py
A80: F071 | B80: P4: LINE/通知基盤 | C80: レポート | D80: 6 | E80: 8:40候補通知 (実行候補1〜3) | F80: 朝5候補から1〜3銘柄厳選。戦略コメント(方針/条件/見送り/利確/損切/監視理由/時間帯)付与。 | G80: 高 | H80: F070 | I80: Claude | J80: 1.5 | K80: 未着手 | N80: reports/candidate_final.py
A81: F072 | B81: P4: LINE/通知基盤 | C81: レポート | D81: 6 | E81: 引け後レビュー (16:00送信) | F81: 売買履歴/実現損益/良し悪し/改善点/再発防止/目標進捗乖離/ポートフォリオ変化。PDF。 | G81: 高 | H81: F061 | I81: Claude | J81: 2 | K81: 未着手 | N81: reports/closing.py
A82: F110 | B82: P4: LINE/通知基盤 | C82: Agent | D82: 4 | E82: Market Intelligence Agent | F82: 朝の市況/ニュース/セクター分析。朝レポート生成。 | G82: 高 | H82: F021,F022,F102 | I82: Claude | J82: 3 | K82: 未着手 | N82: agents/market_intel.py
A83: F117 | B83: P4: LINE/通知基盤 | C83: Agent | D83: 4,6 | E83: Review & Journal Agent | F83: 引け後レビュー、成績分析、学習データ保存。 | G83: 高 | H83: F072 | I83: Claude | J83: 2 | K83: 未着手 | N83: agents/review.py
A84: F118 | B84: P4: LINE/通知基盤 | C84: Agent | D84: 4,1 | E84: Goal Tracking Agent | F84: 3000万円目標の進捗・乖離管理(日週月次)。±5%〜-20%の5段階判定。 | G84: 高 | H84: F088 | I84: Claude | J84: 1.5 | K84: 未着手 | N84: agents/goal_tracking.py
A85: F120 | B85: P4: LINE/通知基盤 | C85: Agent | D85: 13 | E85: Evaluation評価提案書テンプレ | F85: 3行要約/総合/候補抽出/執行/リスク/エッジ別/システム/改善提案/採用判断候補。NotebookLM風。 | G85: 高 | H85: F119 | I85: Claude | J85: 1.5 | K85: 未着手 | N85: agents/eval_template.py | O85: 後知恵バイアス対策必須
A86: F121 | B86: P4: LINE/通知基盤 | C86: Agent | D86: 13 | E86: Evaluation時間軸(日週月) | F86: 日次:軽微改善 週次:エッジ比較/傾向/ルール修正 月次:勝ち筋/ロット/自動停止/大設計変更。 | G86: 高 | H86: F119 | I86: Claude | J86: 1 | K86: 未着手 | N86: agents/eval_timeframe.py
A87: F142 | B87: P4: LINE/通知基盤 | C87: 執行 | D87: 17 | E87: 価格乖離上限/特買特売禁止/寄り直後制限 | F87: +0.3%/値嵩+20円超で無効。特買・特売中は新規禁止。9:00-9:05は観察優先。 | G87: 高 | H87: F141 | I87: Claude | J87: 1 | K87: 未着手 | N87: execution/limits.py
A88: F143 | B88: P4: LINE/通知基盤 | C88: 執行 | D88: 17 | E88: 部分約定・未約定処理 | F88: 半端約定に逆指値セット。一定時間で未約定分取消。全約定不可時の戦略縮小。 | G88: 高 | H88: F141 | I88: Claude | J88: 1.5 | K88: 未着手 | N88: execution/partial_fill.py
A89: F150 | B89: P4: LINE/通知基盤 | C89: スケジュール | D89: 9,35 | E89: 運用スケジュール実装 | F89: 8:00朝分析/8:30朝レポ/8:40候補/9:00-9:08寄観察/9:08-9:20初動/9:20-10:30前場メイン/.../15:10強制クローズ/16:00レビュー。 | G89: 高 | H89: F012 | I89: Claude | J89: 1.5 | K89: 未着手 | N89: runtime/schedule.py
A90: F210 | B90: P4: LINE/通知基盤 | C90: 目標 | D90: 1,27 | E90: 3000万円2年目標トラッキング | F90: 日・週・月次で乖離率管理。±5%/-5〜-10%/-10〜-20%/-20%以下の5段階判定。 | G90: 高 | H90: F118 | I90: Claude | J90: 1 | K90: 未着手 | N90: goal/tracking.py
A91: F112 | B91: P4: LINE/通知基盤 | C91: Agent | D91: 4,7 | E91: Swing Selection Agent | F91: スイング候補抽出、中期トレンド分析。スコア(業績20/テーマ10/トレンド15/流動性15/RR15/材料10/耐性15)。 | G91: 中 | H91: F031 | I91: Claude | J91: 2 | K91: 未着手 | N91: agents/swing_select.py | O91: 本番自動執行はしない
A92: F113 | B92: P4: LINE/通知基盤 | C92: Agent | D92: 4,7 | E92: Long-term Selection Agent | F92: 高配当・成長株抽出。スコア(配当20/成長25/EPS安定15/財務15/優位10/割安10/増配5)。 | G92: 中 | H92: F031 | I92: Claude | J92: 2 | K92: 未着手 | N92: agents/longterm_select.py | O92: 通知・提案のみ
A93: F114 | B93: P4: LINE/通知基盤 | C93: Agent | D93: 4 | E93: Portfolio Balance Agent | F93: セクター偏り点検、バランス改善提案。テーマ集中/大型偏重検知。 | G93: 中 | H93: F111,F112,F113 | I93: Claude | J93: 1.5 | K93: 未着手 | N93: agents/portfolio.py
A94: F080 | B94: P5: Dashboard | C94: UI | D94: 13 | E94: Dashboard フロントエンド骨組み | F94: Next.js/React。レトロCRT炎テーマ。LP的装飾よりトレーディングコンソール実用性優先。 | G94: 最優先 | H94: F001 | I94: Claude | J94: 3 | K94: 未着手 | N94: dashboard/
A95: F081 | B95: P5: Dashboard | C95: UI | D95: 13 | E95: Dashboard 7ブロック構成 | F95: A:ヘッダーサマリー B:今日の運用 C:エッジ別成績 D:候補抽出/執行品質 E:リスク/PF F:Evaluation提案 G:システム状態。 | G95: 最優先 | H95: F080 | I95: Claude | J95: 4 | K95: 未着手 | N95: dashboard/components/
A96: F090 | B96: P5: Dashboard | C96: API | D96: - | E96: Dashboard BackendAPI | F96: FastAPI/Express。Pattern Store/Feature Store/各種ログからデータ供給。 | G96: 最優先 | H96: F011 | I96: Claude | J96: 3 | K96: 未着手 | N96: dashboard/api/
A97: F082 | B97: P5: Dashboard | C97: UI | D97: 12,13 | E97: 昇格ブロッカー常時表示 (赤字警告) | F97: ダッシュボード上部に現在昇格を阻害している条件を赤字で常時表示。 | G97: 高 | H97: F081,F053 | I97: Claude | J97: 0.5 | K97: 未着手 | N97: dashboard/components/Blocker.tsx
A98: F083 | B98: P5: Dashboard | C98: UI | D98: 13 | E98: 初期10KPI表示 | F98: 今日損益/累積/目標乖離/実行候補/主戦略勝率/建玉/稼働状態/承認待ち/停止理由/Eval提案数。 | G98: 高 | H98: F081 | I98: Claude | J98: 2 | K98: 未着手 | N98: dashboard/components/KPI.tsx
A99: F084 | B99: P5: Dashboard | C99: UI | D99: 13,18 | E99: エッジ別成績ビュー | F99: 材料初動型/主役テーマ前場初動型/準スキャル/スイング/長期の勝率・平均損益・RR・最大損失・件数。 | G99: 高 | H99: F081 | I99: Claude | J99: 2 | K99: 未着手 | N99: dashboard/components/EdgeScore.tsx
A100: F085 | B100: P5: Dashboard | C100: UI | D100: 13,17 | E100: 執行品質可視化ブロック | F100: 想定vs実約定/乖離率/部分約定率/未約定率/損切スリッページ/利確スリッページ/強制クローズ率/品質スコア。 | G100: 高 | H100: F081 | I100: Claude | J100: 2 | K100: 未着手 | N100: dashboard/components/Execution.tsx
...

Sheet Phase_Summary
A1: FIRE 開発 — フェーズ別進捗サマリー
A3: フェーズ | B3: 総タスク数 | C3: 完了 | D3: 実装中+検証中 | E3: 未着手 | F3: 完了率
A4: P0: 基盤・環境構築 | B4: =COUNTIF(TODO_Master!B2:B126,A4) -> 19 | C4: =COUNTIFS(TODO_Master!B2:B126,A4,TODO_Master!K2:K126,"完了") -> 19 | D4: =COUNTIFS(TODO_Master!B2:B126,A4,TODO_Master!K2:K126,"実装中")+COUNTIFS(TODO_Master!B2:B126,A4,TODO_Master!K2:K126,"検証中")+COUNTIFS(TODO_Master!B2:B126,A4,TODO_Master!K2:K126,"設計中") -> 0 | E4: =COUNTIFS(TODO_Master!B2:B126,A4,TODO_Master!K2:K126,"未着手") -> 0 | F4: =IFERROR(C4/B4,0) -> 1
A5: P1: Pattern/Feature Store | B5: =COUNTIF(TODO_Master!B2:B126,A5) -> 26 | C5: =COUNTIFS(TODO_Master!B2:B126,A5,TODO_Master!K2:K126,"完了") -> 18 | D5: =COUNTIFS(TODO_Master!B2:B126,A5,TODO_Master!K2:K126,"実装中")+COUNTIFS(TODO_Master!B2:B126,A5,TODO_Master!K2:K126,"検証中")+COUNTIFS(TODO_Master!B2:B126,A5,TODO_Master!K2:K126,"設計中") -> 0 | E5: =COUNTIFS(TODO_Master!B2:B126,A5,TODO_Master!K2:K126,"未着手") -> 8 | F5: =IFERROR(C5/B5,0) -> 0.69230769
A6: P2: Simulation/Backtest | B6: =COUNTIF(TODO_Master!B2:B126,A6) -> 8 | C6: =COUNTIFS(TODO_Master!B2:B126,A6,TODO_Master!K2:K126,"完了") -> 0 | D6: =COUNTIFS(TODO_Master!B2:B126,A6,TODO_Master!K2:K126,"実装中")+COUNTIFS(TODO_Master!B2:B126,A6,TODO_Master!K2:K126,"検証中")+COUNTIFS(TODO_Master!B2:B126,A6,TODO_Master!K2:K126,"設計中") -> 0 | E6: =COUNTIFS(TODO_Master!B2:B126,A6,TODO_Master!K2:K126,"未着手") -> 8 | F6: =IFERROR(C6/B6,0) -> 0
A7: P3: Paper Live | B7: =COUNTIF(TODO_Master!B2:B126,A7) -> 4 | C7: =COUNTIFS(TODO_Master!B2:B126,A7,TODO_Master!K2:K126,"完了") -> 0 | D7: =COUNTIFS(TODO_Master!B2:B126,A7,TODO_Master!K2:K126,"実装中")+COUNTIFS(TODO_Master!B2:B126,A7,TODO_Master!K2:K126,"検証中")+COUNTIFS(TODO_Master!B2:B126,A7,TODO_Master!K2:K126,"設計中") -> 0 | E7: =COUNTIFS(TODO_Master!B2:B126,A7,TODO_Master!K2:K126,"未着手") -> 4 | F7: =IFERROR(C7/B7,0) -> 0
A8: P4: LINE/通知基盤 | B8: =COUNTIF(TODO_Master!B2:B126,A8) -> 35 | C8: =COUNTIFS(TODO_Master!B2:B126,A8,TODO_Master!K2:K126,"完了") -> 0 | D8: =COUNTIFS(TODO_Master!B2:B126,A8,TODO_Master!K2:K126,"実装中")+COUNTIFS(TODO_Master!B2:B126,A8,TODO_Master!K2:K126,"検証中")+COUNTIFS(TODO_Master!B2:B126,A8,TODO_Master!K2:K126,"設計中") -> 0 | E8: =COUNTIFS(TODO_Master!B2:B126,A8,TODO_Master!K2:K126,"未着手") -> 35 | F8: =IFERROR(C8/B8,0) -> 0
A9: P5: Dashboard | B9: =COUNTIF(TODO_Master!B2:B126,A9) -> 12 | C9: =COUNTIFS(TODO_Master!B2:B126,A9,TODO_Master!K2:K126,"完了") -> 0 | D9: =COUNTIFS(TODO_Master!B2:B126,A9,TODO_Master!K2:K126,"実装中")+COUNTIFS(TODO_Master!B2:B126,A9,TODO_Master!K2:K126,"検証中")+COUNTIFS(TODO_Master!B2:B126,A9,TODO_Master!K2:K126,"設計中") -> 0 | E9: =COUNTIFS(TODO_Master!B2:B126,A9,TODO_Master!K2:K126,"未着手") -> 12 | F9: =IFERROR(C9/B9,0) -> 0
A10: P6: 証券API連携 | B10: =COUNTIF(TODO_Master!B2:B126,A10) -> 8 | C10: =COUNTIFS(TODO_Master!B2:B126,A10,TODO_Master!K2:K126,"完了") -> 0 | D10: =COUNTIFS(TODO_Master!B2:B126,A10,TODO_Master!K2:K126,"実装中")+COUNTIFS(TODO_Master!B2:B126,A10,TODO_Master!K2:K126,"検証中")+COUNTIFS(TODO_Master!B2:B126,A10,TODO_Master!K2:K126,"設計中") -> 0 | E10: =COUNTIFS(TODO_Master!B2:B126,A10,TODO_Master!K2:K126,"未着手") -> 8 | F10: =IFERROR(C10/B10,0) -> 0
A11: P7: Live Advisory | B11: =COUNTIF(TODO_Master!B2:B126,A11) -> 6 | C11: =COUNTIFS(TODO_Master!B2:B126,A11,TODO_Master!K2:K126,"完了") -> 0 | D11: =COUNTIFS(TODO_Master!B2:B126,A11,TODO_Master!K2:K126,"実装中")+COUNTIFS(TODO_Master!B2:B126,A11,TODO_Master!K2:K126,"検証中")+COUNTIFS(TODO_Master!B2:B126,A11,TODO_Master!K2:K126,"設計中") -> 0 | E11: =COUNTIFS(TODO_Master!B2:B126,A11,TODO_Master!K2:K126,"未着手") -> 6 | F11: =IFERROR(C11/B11,0) -> 0
A12: P8: Full Auto(将来) | B12: =COUNTIF(TODO_Master!B2:B126,A12) -> 7 | C12: =COUNTIFS(TODO_Master!B2:B126,A12,TODO_Master!K2:K126,"完了") -> 0 | D12: =COUNTIFS(TODO_Master!B2:B126,A12,TODO_Master!K2:K126,"実装中")+COUNTIFS(TODO_Master!B2:B126,A12,TODO_Master!K2:K126,"検証中")+COUNTIFS(TODO_Master!B2:B126,A12,TODO_Master!K2:K126,"設計中") -> 0 | E12: =COUNTIFS(TODO_Master!B2:B126,A12,TODO_Master!K2:K126,"未着手") -> 7 | F12: =IFERROR(C12/B12,0) -> 0
A13: P9: 運用・保守 | B13: =COUNTIF(TODO_Master!B2:B126,A13) -> 0 | C13: =COUNTIFS(TODO_Master!B2:B126,A13,TODO_Master!K2:K126,"完了") -> 0 | D13: =COUNTIFS(TODO_Master!B2:B126,A13,TODO_Master!K2:K126,"実装中")+COUNTIFS(TODO_Master!B2:B126,A13,TODO_Master!K2:K126,"検証中")+COUNTIFS(TODO_Master!B2:B126,A13,TODO_Master!K2:K126,"設計中") -> 0 | E13: =COUNTIFS(TODO_Master!B2:B126,A13,TODO_Master!K2:K126,"未着手") -> 0 | F13: =IFERROR(C13/B13,0) -> 0
A14: 合計 | B14: =SUM(B4:B13) -> 125 | C14: =SUM(C4:C13) -> 37 | D14: =SUM(D4:D13) -> 0 | E14: =SUM(E4:E13) -> 88 | F14: =IFERROR(C14/B14,0) -> 0.296
A17: 優先度別サマリー
A18: 優先度 | B18: 総タスク数 | C18: 完了 | D18: 実装中+検証中 | E18: 未着手 | F18: 完了率
A19: 最優先 | B19: =COUNTIF(TODO_Master!G2:G126,A19) -> 52 | C19: =COUNTIFS(TODO_Master!G2:G126,A19,TODO_Master!K2:K126,"完了") -> 24 | D19: =COUNTIFS(TODO_Master!G2:G126,A19,TODO_Master!K2:K126,"実装中")+COUNTIFS(TODO_Master!G2:G126,A19,TODO_Master!K2:K126,"検証中")+COUNTIFS(TODO_Master!G2:G126,A19,TODO_Master!K2:K126,"設計中") -> 0 | E19: =COUNTIFS(TODO_Master!G2:G126,A19,TODO_Master!K2:K126,"未着手") -> 28 | F19: =IFERROR(C19/B19,0) -> 0.46153846
A20: 高 | B20: =COUNTIF(TODO_Master!G2:G126,A20) -> 55 | C20: =COUNTIFS(TODO_Master!G2:G126,A20,TODO_Master!K2:K126,"完了") -> 13 | D20: =COUNTIFS(TODO_Master!G2:G126,A20,TODO_Master!K2:K126,"実装中")+COUNTIFS(TODO_Master!G2:G126,A20,TODO_Master!K2:K126,"検証中")+COUNTIFS(TODO_Master!G2:G126,A20,TODO_Master!K2:K126,"設計中") -> 0 | E20: =COUNTIFS(TODO_Master!G2:G126,A20,TODO_Master!K2:K126,"未着手") -> 42 | F20: =IFERROR(C20/B20,0) -> 0.23636364
A21: 中 | B21: =COUNTIF(TODO_Master!G2:G126,A21) -> 11 | C21: =COUNTIFS(TODO_Master!G2:G126,A21,TODO_Master!K2:K126,"完了") -> 0 | D21: =COUNTIFS(TODO_Master!G2:G126,A21,TODO_Master!K2:K126,"実装中")+COUNTIFS(TODO_Master!G2:G126,A21,TODO_Master!K2:K126,"検証中")+COUNTIFS(TODO_Master!G2:G126,A21,TODO_Master!K2:K126,"設計中") -> 0 | E21: =COUNTIFS(TODO_Master!G2:G126,A21,TODO_Master!K2:K126,"未着手") -> 11 | F21: =IFERROR(C21/B21,0) -> 0
A22: 低 | B22: =COUNTIF(TODO_Master!G2:G126,A22) -> 7 | C22: =COUNTIFS(TODO_Master!G2:G126,A22,TODO_Master!K2:K126,"完了") -> 0 | D22: =COUNTIFS(TODO_Master!G2:G126,A22,TODO_Master!K2:K126,"実装中")+COUNTIFS(TODO_Master!G2:G126,A22,TODO_Master!K2:K126,"検証中")+COUNTIFS(TODO_Master!G2:G126,A22,TODO_Master!K2:K126,"設計中") -> 0 | E22: =COUNTIFS(TODO_Master!G2:G126,A22,TODO_Master!K2:K126,"未着手") -> 7 | F22: =IFERROR(C22/B22,0) -> 0

Sheet 開発・運用フェーズ計画
A1: 開発フェーズ(D) と 運用フェーズ(M) の関係
A2: Mac mini 到着待ちの期間を有効活用するための開発・運用フェーズ分離計画
A4: ■ 開発フェーズ (Windows PCで進行可)
A5: Dev Phase | B5: 名称 | C5: 主要タスク | D5: OS依存 | E5: プラットフォーム | F5: Mac mini必要？
A6: D1 | B6: 基盤・環境構築 | C6: F001(Win環境) F004(Gitリポ) F005(CLAUDE.md) F006(README.md) F007(Obsidian) F008(ディレクトリ) F009(.env) F010(ログ) F011(DB) F014(クロスPF設計) | D6: なし | E6: Windows PC | F6: 不要
A7: D2 | B7: Pattern/Feature Store実装 | C7: F020〜F038(Feature Store, Pattern Store 4階層, DEATH NOTE, REHAB, Pattern Research Agent) | D7: なし | E7: Windows PC | F7: 不要
A8: D3 | B8: Simulation/Backtest/Paper Liveロジック | C8: F040〜F053(Backtest, Replay, 3約定モデル, 高速リプレイ並列, Paper Live本体, 仮想管理) | D8: なし(Python計算) | E8: Windows PC | F8: 不要
A9: D4 | B9: エージェント群+LINE通知+Dashboard | C9: F060〜F090(LINE連携, 朝/引けレポート), F110〜F121(10エージェント), F080〜F090(Dashboard) | D9: なし(Python/Node) | E9: Windows PC | F9: 不要
A10: D5 | B10: リスク管理・執行品質・5層防御・ラベル定義 | C10: F130〜F144(リスク/執行ゲート/スリッページ監視), F160〜F164(5層防御), F180〜F183(ラベル) | D10: なし | E10: Windows PC | F10: 不要
A11: D6 | B11: 証券API連携+縮退運転 | C11: F100〜F107(市場データ/TDnet/News/TradingView/楽天API/縮退5段階) | D11: なし(API接続) | E11: Windows PC | F11: 不要
A12: D7 | B12: Windows擬似運用でPaper Live検証 | C12: F015(Winタスクスケジューラ)で日中Paper Live動作確認・不具合洗い出し | D12: Windows固有 | E12: Windows PC | F12: 不要
A13: D8 | B13: Mac mini移行 | C13: F002(Mac初期設定) F003(開発環境) F013(launchd) F016(移行チェック) | D13: Mac固有 | E13: Mac mini | F13: 必須
A16: ■ 運用フェーズ (Mac mini到着後に開始)
A17: Ops Phase | B17: Stage | C17: 実弾 | D17: デイトレリスク | E17: 主要アクション | F17: 前提条件
A18: M-3 〜 M-1 | B18: Stage 0/1/2 | C18: 未投入 | D18: — | E18: Mac mini常時稼働で過去データ高速リプレイ+Paper Live並列実行。パターン爆速蓄積。 | F18: D1-D8完了 / Mac mini常駐化完了
A19: M=0 (運用初月) | B19: Stage 3 Semi Auto | C19: 投入 | D19: 0.2% (半減) | E19: 執行実測データ収集。初月から黒字化目標。 | F19: Paper→Semi昇格基準クリア
A20: M+1 | B20: Stage 3 Semi Auto | C20: 投入 | D20: 0.3% | E20: リスク枠拡大。Pattern Libraryの浄化開始。 | F20: 執行乖離が想定内
A21: M+2 | B21: Stage 3 Semi Auto | C21: 投入 | D21: 0.4% (フルリスク) | E21: フルリスク運用。期待値安定化。 | F21: 継続的な期待値プラス
A22: M+3 以降 | B22: Stage 4 部分Full Auto | C22: 投入 | D22: 0.4% | E22: デイトレSランクのみFull Auto。スイング・長期はSemi Auto維持。 | F22: Semi→Full昇格基準クリア
A25: ■ 重要な考え方
A26: 1. Mac mini到着までの期間は、D1〜D7 の開発作業に最大限使う。コード実装・テスト・Simulation検証までWindows PCで完結可能。
A27: 2. D8 (Mac mini移行) は、Mac mini到着後に短期間で一気に実施。F002→F003→F013→F016の順。
A28: 3. M-3 (運用立ち上げ・パターン爆速蓄積) は、Mac mini常駐化後に正式スタート。Mac到着遅延がM=0を後ろ倒しする。
A29: 4. ただしWindows PC上でもD7(擬似Paper Live検証)でPattern Storeの仮蓄積は可能。Macに移行した時点で過去データリプレイも高速実行できる。
A30: 5. 要件書15章の「Pattern Store最優先→Paper Live→証券API」の順序は維持。証券API(F104)もWindows PCで実装可能だが、本番実弾はMac miniに移行後。
A31: 6. Mac mini到着が遅れるほど、D1-D7の完成度を上げる時間が増える。これは要件書39章のM-3(爆速蓄積)の期間を実質前倒しすることに相当する。

Sheet Agent_Checklist
A1: FIRE 10エージェント 実装チェックリスト
A3: エージェント名 | B3: 責務 | C3: 関連タスクID | D3: 実装ファイル | E3: ステータス
A4: Market Intelligence Agent | B4: 朝の市況・ニュース・セクター分析、朝レポート生成 | C4: F110, F070 | D4: agents/market_intel.py | E4: 未着手
A5: Daytrade Selection Agent | B5: デイトレ候補抽出・厳選(1〜3銘柄)、スコア付与 | C5: F111, F200 | D5: agents/daytrade_select.py | E5: 未着手
A6: Swing Selection Agent | B6: スイング候補抽出、中期トレンド分析 | C6: F112 | D6: agents/swing_select.py | E6: 未着手
A7: Long-term Selection Agent | B7: 高配当・成長株抽出、長期スコア付与 | C7: F113 | D7: agents/longterm_select.py | E7: 未着手
A8: Portfolio Balance Agent | B8: セクター偏り点検、バランス改善提案 | C8: F114 | D8: agents/portfolio.py | E8: 未着手
A9: Trade Decision Agent | B9: エントリー/利確/損切/株数提案、リスク計算、注文案生成 | C9: F115, F130 | D9: agents/trade_decision.py | E9: 未着手
A10: Monitoring & Alert Agent | B10: 価格到達監視、LINE通知発火 | C10: F116, F061 | D10: agents/monitoring.py | E10: 未着手
A11: Review & Journal Agent | B11: 引け後レビュー、成績分析、学習データ保存 | C11: F117, F072 | D11: agents/review.py | E11: 未着手
A12: Goal Tracking Agent | B12: 3000万円目標進捗・乖離管理(日週月次) | C12: F118, F210 | D12: agents/goal_tracking.py | E12: 未着手
A13: Evaluation Agent | B13: 評価提案書作成(自動反映禁止・承認制) | C13: F119, F120, F121 | D13: agents/evaluation.py | E13: 未着手
A14: Pattern Research Agent | B14: パターン発見・定義・更新提案(研究責任者) | C14: F035, F036 | D14: agents/pattern_research.py | E14: 未着手

Sheet Stage_Gate
A1: Stage 昇格ゲート チェックリスト(要件書32章・34章)
A3: Stage移行 | B3: 条件 | C3: 基準 | D3: 判定方法 | E3: 状態
A4: Stage0→1 (Backtest→Replay) | B4: 戦略ロジックが動作する | C4: Backtestで候補抽出/損益計算が回る | D4: simulation/backtest.py 実行 | E4: 未達
A5: Stage1→2 (Replay→Paper Live) | B5: 後知恵バイアス排除検証済 | C5: Replayで当時情報のみで判断できる | D5: simulation/replay.py 実行 | E5: 未達
A6: Stage2→3 (Paper→Semi Auto) | B6: サンプル数 | C6: 20営業日 or 50トレード(過去高速リプレイで短縮可) | D6: promotion_check.py | E6: 未達
B7: 主戦略期待値 | C7: expectancy > 0 | D7: expectancy計算 | E7: 未達
B8: 最大DD | C8: 総資産比 -5% を大きく超えない | D8: DD計算 | E8: 未達
B9: 強制クローズ成功率 | C9: 100% | D9: force_close テスト | E9: 未達
B10: 停止機能 | C10: 日次/週次損失上限・緊急停止正常動作 | D10: 統合テスト | E10: 未達
B11: Optimistic Bias | C11: 許容範囲内 | D11: bias_score.py | E11: 未達
B12: Evaluation Agent確認 | C12: 明確な改善提案が残っていない | D12: Evaluation承認 | E12: 未達
A13: Stage3→4 (Semi→Full Auto) | B13: Semi Auto実績 | C13: 20営業日 or 50実注 | D13: 実注履歴 | E13: 未達
B14: 実約定期待値 | C14: expectancy > 0 (実約定ベース) | D14: 実績集計 | E14: 未達
B15: 平均スリッページ | C15: avg_slippage 許容範囲内 | D15: slippage監視 | E15: 未達
B16: 強制クローズ成功率 | C16: 100% | D16: 実績確認 | E16: 未達
B17: システム稼働率 | C17: broker_uptime/system_uptime 十分 | D17: health監視 | E17: 未達
B18: Evaluation昇格提案 | C18: 昇格推奨が出る | D18: promotion_report.py | E18: 未達
B19: ユーザー承認 | C19: 必ずユーザーが最終承認 | D19: 手動承認 | E19: 未達
A20: 昇格禁止条件(共通) | B20: 期待値マイナス/DD過大/Bias高/クローズ失敗/緊急停止動作不良/主戦略件数不足/執行品質悪化/監督負荷高 | C20: いずれか該当で昇格禁止 | D20: block_rules.py | E20: —

Sheet Roadmap
A1: 運用立ち上げロードマップ (要件書39章)
A3: 期間 | B3: Stage | C3: 実弾 | D3: デイトレリスク | E3: 主要アクション | F3: 完了条件
A4: M-3 〜 M-1 | B4: Stage 0/1/2 | C4: 未投入 | D4: — | E4: Mac mini常時稼働で過去データ高速リプレイ+Paper Live並列実行。パターン爆速蓄積。 | F4: Paper→Semi昇格条件を全てクリア
A5: M=0 (運用初月) | B5: Stage 3 (Semi Auto) | C5: 投入 | D5: 0.2% (半減) | E5: 執行実測データ収集。初月から黒字化目標。 | F5: 執行乖離が想定内・20営業日経過
A6: M+1 | B6: Stage 3 (Semi Auto) | C6: 投入 | D6: 0.3% | E6: リスク枠拡大。Pattern Libraryの浄化開始。 | F6: 継続的な期待値プラス
A7: M+2 | B7: Stage 3 (Semi Auto) | C7: 投入 | D7: 0.4% (要件書通り) | E7: フルリスク運用。期待値安定化。 | F7: Semi→Full昇格条件クリア
A8: M+3 以降 | B8: Stage 4 (部分 Full Auto) | C8: 投入 | D8: 0.4% | E8: デイトレSランクのみFull Auto。スイング・長期はSemi Auto維持。 | F8: —

Sheet Risk_Holes
A1: 要件書で特定された「穴」と対策チェック (穴1〜12)
A3: 穴 | B3: 問題 | C3: 対策(章) | D3: 対応タスクID
A4: 穴1: エッジが弱い | B4: エッジの根拠が曖昧 | C4: 再現性優位で定義 (26章) | D4: F031, F032, F200
A5: 穴2: 約定品質 | B5: 執行品質が悪い | C5: 執行品質ゲート (17章) | D5: F140, F141, F142, F143, F144
A6: 穴3: データソース依存 | B6: 依存先が死ぬと事故 | C6: 縮退運転 (22章) | D6: F106, F107
A7: 穴4: 広げすぎ | B7: 最初の焦点がぼやける | C7: 主戦略集中 (24章) | D7: F200, F201
A8: 穴5: 目標で攻めすぎ | B8: 目標圧力で規律崩壊 | C8: 目標と攻撃性を分離 (27章) | D8: F210, F211
A9: 穴6: 完全放置 | B9: 無監督化で事故 | C9: 監督者付き自律運用 (28章) | D9: F164, F173
A10: 穴7: ラベル曖昧 | B10: 成功/失敗定義が弱い | C10: Success/Failure/Timeout/Invalid 4分類 (29章) | D10: F180, F181, F182, F183
A11: 穴8: 特徴量過多 | B11: 類似局面見つからない/過剰適合 | C11: 初期は最小コアセットに絞る (30章) | D11: F020, F021, F022, F023, F024, F025, F026
A12: 穴9: Pattern Store品質 | B12: 重複・似すぎ・名前違いが増える | C12: 命名規則/統合ルール/バージョン管理 (31章) | D12: F030, F037
A13: 穴10: 本番移行基準 | B13: 昇格基準が曖昧 | C13: 完全版昇格条件 (32章) | D13: F190, F191, F192, F193
A14: 穴11: 運用負荷上限 | B14: 提案/通知/承認が多すぎて疲れる | C14: 通知階層化・承認最小化・初期KPI絞り込み (33章) | D14: F063, F083, F172
A15: 穴12: セクター/銘柄特有性 | B15: パターンが銘柄・セクター個別性を表現できない | C15: sector_filter/symbol_whitelistでパターン絞込み (21章) | D15: F039, F243

Sheet RTM_要件カバレッジ
A1: 要件トレーサビリティマトリクス (RTM) — 要件書 v3.1 全要件とタスクIDの対応
A2: 使い方: E列「タスク紐付け件数」が0の行は赤ハイライト(抜け漏れ)。要件をタスク化するか、理由を記載する。
A4: 要件ID | B4: 章 | C4: 節タイトル | D4: 要件内容 | E4: 対応タスクID | F4: タスク紐付け件数
A5: R-01-01 | B5: 1 | C5: プロダクト名 FIRE | D5: 日本株専門AIエージェントシステム | E5: F005, F006 | F5: =IF(TRIM(E5)="",0,LEN(E5)-LEN(SUBSTITUTE(E5,",",""))+1) -> 2
A6: R-01-02 | B6: 1 | C6: UIテーマ: レトロCRT炎 | D6: ダーク高級路線ではなく昔のブローカー端末風 | E6: F080 | F6: =IF(TRIM(E6)="",0,LEN(E6)-LEN(SUBSTITUTE(E6,",",""))+1) -> 1
A7: R-01-03 | B7: 1 | C7: 最重要目的: 兼業前提の月次年次利益最大化 | D7: LINE通知で発注完結、再現性高く利益最大化 | E7: F062, F070, F071 | F7: =IF(TRIM(E7)="",0,LEN(E7)-LEN(SUBSTITUTE(E7,",",""))+1) -> 3
A8: R-01-04 | B8: 1 | C8: 資産目標: 2年で3000万円 | D8: 目標未達時も無謀なリスク拡大禁止 | E8: F210, F211 | F8: =IF(TRIM(E8)="",0,LEN(E8)-LEN(SUBSTITUTE(E8,",",""))+1) -> 2
A9: R-01-05 | B9: 1 | C9: 乖離率5段階判定(+5%/±5%内/-10%/-20%/再設計) | D9: 日・週・月次で管理 | E9: F118, F210 | F9: =IF(TRIM(E9)="",0,LEN(E9)-LEN(SUBSTITUTE(E9,",",""))+1) -> 2
A10: R-01-06 | B10: 1 | C10: v3.1アップデート: 運用立ち上げロードマップ | D10: M-3〜M+3までのリスク逓増 | E10: F220, F221, F222, F223, F224 | F10: =IF(TRIM(E10)="",0,LEN(E10)-LEN(SUBSTITUTE(E10,",",""))+1) -> 5
A11: R-01-07 | B11: 1 | C11: v3.1: 過去データ高速リプレイ並列実行 | D11: Stage昇格日数短縮 | E11: F045 | F11: =IF(TRIM(E11)="",0,LEN(E11)-LEN(SUBSTITUTE(E11,",",""))+1) -> 1
A12: R-01-08 | B12: 1 | C12: v3.1: Full Auto時 5層防御 | D12: シグナルベース重複防御 | E12: F160, F161, F162, F163, F164 | F12: =IF(TRIM(E12)="",0,LEN(E12)-LEN(SUBSTITUTE(E12,",",""))+1) -> 5
A13: R-01-09 | B13: 1 | C13: v3.1: 執行品質段階的アラート+自己キャリブレーション | D13: 実測値ベース | E13: F144 | F13: =IF(TRIM(E13)="",0,LEN(E13)-LEN(SUBSTITUTE(E13,",",""))+1) -> 1
A14: R-01-10 | B14: 1 | C14: v3.1: 主戦略80%/準戦略20% 優先順位 | D14: M+2までPaper並走 | E14: F200 | F14: =IF(TRIM(E14)="",0,LEN(E14)-LEN(SUBSTITUTE(E14,",",""))+1) -> 1
A15: R-01-11 | B15: 1 | C15: v3.1: ハイブリッド執行方針 | D15: Sランク材料=逆指値→成行、通常=指値主体 | E15: F141 | F15: =IF(TRIM(E15)="",0,LEN(E15)-LEN(SUBSTITUTE(E15,",",""))+1) -> 1
A16: R-01-12 | B16: 1 | C16: v3.1: Paper Live厳しめ約定モデル | D16: +2ティック/値嵩1.5倍/寄り直後1.5倍 | E16: F044, F052 | F16: =IF(TRIM(E16)="",0,LEN(E16)-LEN(SUBSTITUTE(E16,",",""))+1) -> 2
... A18: R-01-14 | B18: 1 | C18: v3.1: 強制クローズ独立プロセス | D18: 別ファイル+Cronフェイルセーフ | E18: F133 | F18: =IF(TRIM(E18)="",0,LEN(E18)-LEN(SUBSTITUTE(E18,",",""))+1) -> 1
A19: R-02-01 | B19: 2 | C19: 日本株専門・兼業投資家 | D19: 現物・信用両方使用 | F19: =IF(TRIM(E19)="",0,LEN(E19)-LEN(SUBSTITUTE(E19,",",""))+1) -> 0
A20: R-02-02 | B20: 2 | C20: デイトレ: 信用取引/値嵩株中心/プライム | D20: 流動性・テーマ性・値動き明確さ | E20: F111 | F20: =IF(TRIM(E20)="",0,LEN(E20)-LEN(SUBSTITUTE(E20,",",""))+1) -> 1
A21: R-02-03 | B21: 2 | C21: スイング: 現物中心/中期トレンド | D21: 波動継続性・RR・PF補完 | E21: F112 | F21: =IF(TRIM(E21)="",0,LEN(E21)-LEN(SUBSTITUTE(E21,",",""))+1) -> 1
A22: R-02-04 | B22: 2 | C22: 長期: 現物/高配当・成長株 | D22: 配当3%以上・営業利益成長3年以上 | E22: F113 | F22: =IF(TRIM(E22)="",0,LEN(E22)-LEN(SUBSTITUTE(E22,",",""))+1) -> 1
A23: R-02-05 | B23: 2 | C23: 長期の増配継続は加点のみ(必須ではない) | E23: F113 | F23: =IF(TRIM(E23)="",0,LEN(E23)-LEN(SUBSTITUTE(E23,",",""))+1) -> 1
A24: R-03-01 | B24: 3 | C24: 主戦略2本柱(レーン1) | D24: 高品質材料初動・主役テーマ連動値嵩株前場初動 | E24: F200 | F24: =IF(TRIM(E24)="",0,LEN(E24)-LEN(SUBSTITUTE(E24,",",""))+1) -> 1
A25: R-03-02 | B25: 3 | C25: 高品質材料の初動 | D25: 好決算/上方修正/増配/自社株買い/進捗/資本政策/受注/提携/政策 | E25: F021, F111 | F25: =IF(TRIM(E25)="",0,LEN(E25)-LEN(SUBSTITUTE(E25,",",""))+1) -> 2
A26: R-03-03 | B26: 3 | C26: 決算シーズンの母集団広・実行候補1-3固定 | D26: 通常より厳しいフィルター | E26: F202 | F26: =IF(TRIM(E26)="",0,LEN(E26)-LEN(SUBSTITUTE(E26,",",""))+1) -> 1
A27: R-03-04 | B27: 3 | C27: 主役テーマ連動の値嵩株前場初動 | D27: 決算期以外の安定頻度確保の本命 | E27: F111, F200 | F27: =IF(TRIM(E27)="",0,LEN(E27)-LEN(SUBSTITUTE(E27,",",""))+1) -> 2
A28: R-03-05 | B28: 3 | C28: 準主戦略(レーン2) | D28: 前日強かった主役押し目再加速/セクター主役続伸初押し/前場ブレイク再試行 | E28: F200 | F28: =IF(TRIM(E28)="",0,LEN(E28)-LEN(SUBSTITUTE(E28,",",""))+1) -> 1
A29: R-04-01 | B29: 4 | C29: Mac mini常駐ランタイム前提 | D29: デイトレとスイングは同一エージェントで扱わない | E29: F012, F013 | F29: =IF(TRIM(E29)="",0,LEN(E29)-LEN(SUBSTITUTE(E29,",",""))+1) -> 2
A30: R-04-02 | B30: 4 | C30: Market Intelligence Agent | D30: 朝の市況・ニュース・セクター分析・朝レポート | E30: F110 | F30: =IF(TRIM(E30)="",0,LEN(E30)-LEN(SUBSTITUTE(E30,",",""))+1) -> 1
A31: R-04-03 | B31: 4 | C31: Daytrade Selection Agent | D31: デイトレ候補抽出・厳選1-3銘柄・スコア | E31: F111 | F31: =IF(TRIM(E31)="",0,LEN(E31)-LEN(SUBSTITUTE(E31,",",""))+1) -> 1
A32: R-04-04 | B32: 4 | C32: Swing Selection Agent | D32: スイング候補抽出・中期トレンド | E32: F112 | F32: =IF(TRIM(E32)="",0,LEN(E32)-LEN(SUBSTITUTE(E32,",",""))+1) -> 1
A33: R-04-05 | B33: 4 | C33: Long-term Selection Agent | D33: 高配当・成長株・長期スコア | E33: F113 | F33: =IF(TRIM(E33)="",0,LEN(E33)-LEN(SUBSTITUTE(E33,",",""))+1) -> 1
A34: R-04-06 | B34: 4 | C34: Portfolio Balance Agent | D34: セクター偏り点検・バランス改善提案 | E34: F114 | F34: =IF(TRIM(E34)="",0,LEN(E34)-LEN(SUBSTITUTE(E34,",",""))+1) -> 1
A35: R-04-07 | B35: 4 | C35: Trade Decision Agent | D35: エントリー/利確/損切/株数/リスク計算/注文案 | E35: F115 | F35: =IF(TRIM(E35)="",0,LEN(E35)-LEN(SUBSTITUTE(E35,",",""))+1) -> 1
... A42: R-05-03 | B42: 5 | C42: デイトレM=0 初月0.2%開始 | D42: リスク係数半減 | E42: F131 | F42: =IF(TRIM(E42)="",0,LEN(E42)-LEN(SUBSTITUTE(E42,",",""))+1) -> 1
A43: R-05-04 | B43: 5 | C43: スイング通常0.6%/強気0.8%上限 | E43: F130 | F43: =IF(TRIM(E43)="",0,LEN(E43)-LEN(SUBSTITUTE(E43,",",""))+1) -> 1
A44: R-05-05 | B44: 5 | C44: スイングM=0 初月0.3%開始 | D44: リスク係数半減 | E44: F131 | F44: =IF(TRIM(E44)="",0,LEN(E44)-LEN(SUBSTITUTE(E44,",",""))+1) -> 1
A45: R-05-06 | B45: 5 | C45: 長期1銘柄最大1.2%(分割買い前提) | E45: F130 | F45: =IF(TRIM(E45)="",0,LEN(E45)-LEN(SUBSTITUTE(E45,",",""))+1) -> 1
A46: R-05-07 | B46: 5 | C46: ロット計算式 floor(許容損失÷(ENTRY-STOP)) | D46: 100株単位丸め | E46: F115, F130 | F46: =IF(TRIM(E46)="",0,LEN(E46)-LEN(SUBSTITUTE(E46,",",""))+1) -> 2
A47: R-05-08 | B47: 5 | C47: 日次-1.2%新規停止/-1.8%当日終了 | E47: F132 | F47: =IF(TRIM(E47)="",0,LEN(E47)-LEN(SUBSTITUTE(E47,",",""))+1) -> 1
A48: R-05-09 | B48: 5 | C48: 週次-3.0%守備/-4.0%大幅制限/-5.0%原則停止 | E48: F132 | F48: =IF(TRIM(E48)="",0,LEN(E48)-LEN(SUBSTITUTE(E48,",",""))+1) -> 1
A49: R-05-10 | B49: 5 | C49: 信用建玉15:10必ずクローズ・持越し禁止 | E49: F133 | F49: =IF(TRIM(E49)="",0,LEN(E49)-LEN(SUBSTITUTE(E49,",",""))+1) -> 1
A50: R-05-11 | B50: 5 | C50: 15:00以降新規信用禁止/14:45以降原則禁止 | E50: F133, F142 | F50: =IF(TRIM(E50)="",0,LEN(E50)-LEN(SUBSTITUTE(E50,",",""))+1) -> 2
A51: R-05-12 | B51: 5 | C51: 損切価格未設定のデイトレ禁止 | E51: F115 | F51: =IF(TRIM(E51)="",0,LEN(E51)-LEN(SUBSTITUTE(E51,",",""))+1) -> 1
A52: R-05-13 | B52: 5 | C52: 買付余力超過の発注禁止 | E52: F105 | F52: =IF(TRIM(E52)="",0,LEN(E52)-LEN(SUBSTITUTE(E52,",",""))+1) -> 1
A53: R-05-14 | B53: 5 | C53: 日次損失上限到達後の新規建て禁止 | E53: F132 | F53: =IF(TRIM(E53)="",0,LEN(E53)-LEN(SUBSTITUTE(E53,",",""))+1) -> 1
A54: R-06-01 | B54: 6 | C54: LINE通知 発注完成形 | D54: 見てそのまま発注できるレベル | E54: F062 | F54: =IF(TRIM(E54)="",0,LEN(E54)-LEN(SUBSTITUTE(E54,",",""))+1) -> 1
A55: R-06-02 | B55: 6 | C55: 通知4部屋分離 | D55: エントリー/執行損益/レポート/システム警告 | E55: F061 | F55: =IF(TRIM(E55)="",0,LEN(E55)-LEN(SUBSTITUTE(E55,",",""))+1) -> 1
A56: R-06-03 | B56: 6 | C56: 通知必須項目11個 | D56: 銘柄/区分/行動/価格/株数/逆指値/利確/損切/期限/無効条件/戦略 | E56: F062 | F56: =IF(TRIM(E56)="",0,LEN(E56)-LEN(SUBSTITUTE(E56,",",""))+1) -> 1
A57: R-06-04 | B57: 6 | C57: 200株: 利確2段+逆指値管理 | E57: F062 | F57: =IF(TRIM(E57)="",0,LEN(E57)-LEN(SUBSTITUTE(E57,",",""))+1) -> 1
A58: R-06-05 | B58: 6 | C58: 100株: 利確1回+逆指値管理 | E58: F062 | F58: =IF(TRIM(E58)="",0,LEN(E58)-LEN(SUBSTITUTE(E58,",",""))+1) -> 1
A59: R-06-06 | B59: 6 | C59: 朝レポート(8:30 PDF送信) | D59: NotebookLM風・3行要約/世界情勢/市場/ニュース/5機会/偏り/今日やること | E59: F070 | F59: =IF(TRIM(E59)="",0,LEN(E59)-LEN(SUBSTITUTE(E59,",",""))+1) -> 1
A60: R-06-07 | B60: 6 | C60: ニュースのトレード洞察変換 | D60: 短期/長期影響/価格レンジ/提案ポジショニング | E60: F070 | F60: =IF(TRIM(E60)="",0,LEN(E60)-LEN(SUBSTITUTE(E60,",",""))+1) -> 1
A61: R-06-08 | B61: 6 | C61: 高確率トレード機会5件特定 | D61: ENTRY/利益目標/ストップ/想定RR/根拠 | E61: F070, F071 | F61: =IF(TRIM(E61)="",0,LEN(E61)-LEN(SUBSTITUTE(E61,",",""))+1) -> 2
A62: R-06-09 | B62: 6 | C62: 売買シグナル 買い/ホールド/売り明確化 | D62: 朝レポは詳細推論、LINEは結論のみ | E62: F070, F062 | F62: =IF(TRIM(E62)="",0,LEN(E62)-LEN(SUBSTITUTE(E62,",",""))+1) -> 2
A63: R-06-10 | B63: 6 | C63: 引け後レビュー(16:00 PDF送信) | D63: 売買履歴/実現損益/良し悪し/改善/再発防止/目標乖離/PF変化 | E63: F072 | F63: =IF(TRIM(E63)="",0,LEN(E63)-LEN(SUBSTITUTE(E63,",",""))+1) -> 1
A64: R-07-01 | B64: 7 | C64: デイトレ候補 朝5件→8:40で1-3銘柄厳選 | D64: 候補不足日は0-1銘柄でも可 | E64: F071, F111 | F64: =IF(TRIM(E64)="",0,LEN(E64)-LEN(SUBSTITUTE(E64,",",""))+1) -> 2
A65: R-07-02 | B65: 7 | C65: スイング候補広め | D65: 新規/追加/分散/見送り | E65: F112 | F65: =IF(TRIM(E65)="",0,LEN(E65)-LEN(SUBSTITUTE(E65,",",""))+1) -> 1
A66: R-07-03 | B66: 7 | C66: 長期候補別枠で広め | E66: F113 | F66: =IF(TRIM(E66)="",0,LEN(E66)-LEN(SUBSTITUTE(E66,",",""))+1) -> 1
A67: R-07-04 | B67: 7 | C67: 8:40通知に戦略コメント付与 | D67: 方針/ENTRY条件/見送り条件/利確/損切/監視理由/時間帯 | E67: F071 | F67: =IF(TRIM(E67)="",0,LEN(E67)-LEN(SUBSTITUTE(E67,",",""))+1) -> 1
A68: R-08-01 | B68: 8 | C68: 8:00-8:25 朝分析 | D68: 市況・ニュース・セクター・候補抽出・PF偏り確認 | E68: F150, F110 | F68: =IF(TRIM(E68)="",0,LEN(E68)-LEN(SUBSTITUTE(E68,",",""))+1) -> 2
A69: R-08-02 | B69: 8 | C69: 8:25-8:30 朝レポート送信 | D69: PDF生成・LINE送信 | E69: F070, F150 | F69: =IF(TRIM(E69)="",0,LEN(E69)-LEN(SUBSTITUTE(E69,",",""))+1) -> 2
A70: R-08-03 | B70: 8 | C70: 8:30-8:40 実行候補絞り込み | D70: 朝5候補→1-3銘柄 | E70: F071, F150 | F70: =IF(TRIM(E70)="",0,LEN(E70)-LEN(SUBSTITUTE(E70,",",""))+1) -> 2
A71: R-08-04 | B71: 8 | C71: 8:40 候補通知 | D71: 戦略コメント付き | E71: F071, F150 | F71: =IF(TRIM(E71)="",0,LEN(E71)-LEN(SUBSTITUTE(E71,",",""))+1) -> 2
A72: R-08-05 | B72: 8 | C72: 9:00-9:08 寄り付き観察 | D72: 飛びつき禁止・GU/GD・初動ノイズ警戒 | E72: F142, F150 | F72: =IF(TRIM(E72)="",0,LEN(E72)-LEN(SUBSTITUTE(E72,",",""))+1) -> 2
A73: R-08-06 | B73: 8 | C73: 9:08-9:20 初動判断 | D73: 本命候補のみ監視・条件成立で通知 | E73: F116, F150 | F73: =IF(TRIM(E73)="",0,LEN(E73)-LEN(SUBSTITUTE(E73,",",""))+1) -> 2
A74: R-08-07 | B74: 8 | C74: 9:20-10:30 前場メイン | D74: デイトレ主戦場・新規最優先 | E74: F150 | F74: =IF(TRIM(E74)="",0,LEN(E74)-LEN(SUBSTITUTE(E74,",",""))+1) -> 1
A75: R-08-08 | B75: 8 | C75: 10:30-11:00 前場後半整理 | D75: 伸びない銘柄整理・後場候補仮決定 | E75: F150 | F75: =IF(TRIM(E75)="",0,LEN(E75)-LEN(SUBSTITUTE(E75,",",""))+1) -> 1
A76: R-08-09 | B76: 8 | C76: 11:00-12:20 昼休み分析 | D76: 前場レビュー・後場本命再設定 | E76: F150 | F76: =IF(TRIM(E76)="",0,LEN(E76)-LEN(SUBSTITUTE(E76,",",""))+1) -> 1
A77: R-08-10 | B77: 8 | C77: 12:20-12:35 後場寄り監視 | D77: GU/GD・重要価格帯再確認 | E77: F150 | F77: =IF(TRIM(E77)="",0,LEN(E77)-LEN(SUBSTITUTE(E77,",",""))+1) -> 1
A78: R-08-11 | B78: 8 | C78: 12:35-14:00 後場メイン | D78: 既存ポジション管理優先・新規慎重 | E78: F150 | F78: =IF(TRIM(E78)="",0,LEN(E78)-LEN(SUBSTITUTE(E78,",",""))+1) -> 1
... A83: R-10-01 | B83: 10 | C83: デイトレスコア100点満点 | D83: 地合い15/テーマ15/流動性20/値動き20/値嵩10/RR10/板補助10 | E83: F111 | F83: =IF(TRIM(E83)="",0,LEN(E83)-LEN(SUBSTITUTE(E83,",",""))+1) -> 1
A84: R-10-02 | B84: 10 | C84: デイトレ判定 A80+/B70-79/C60-69/見送り59- | E84: F111 | F84: =IF(TRIM(E84)="",0,LEN(E84)-LEN(SUBSTITUTE(E84,",",""))+1) -> 1
A85: R-10-03 | B85: 10 | C85: スイングスコア100点満点 | D85: 業績20/テーマ10/トレンド15/流動性15/RR15/材料10/耐性15 | E85: F112 | F85: =IF(TRIM(E85)="",0,LEN(E85)-LEN(SUBSTITUTE(E85,",",""))+1) -> 1
A86: R-10-04 | B86: 10 | C86: 長期スコア100点満点 | D86: 配当20/成長25/EPS15/財務15/優位10/割安10/増配5 | E86: F113 | F86: =IF(TRIM(E86)="",0,LEN(E86)-LEN(SUBSTITUTE(E86,",",""))+1) -> 1
A87: R-10-05 | B87: 10 | C87: 初期特徴量6レイヤ構造 | D87: 材料/地合い/出来高/値動き/執行品質/時間帯 | E87: F020, F021, F022, F023, F024, F025, F026 | F87: =IF(TRIM(E87)="",0,LEN(E87)-LEN(SUBSTITUTE(E87,",",""))+1) -> 7
A88: R-11-01 | B88: 11 | C88: 再現性エンジン = 過去DB+類似検索+統計優位判定 | D88: ブラックボックスAIにしない | E88: F031, F032 | F88: =IF(TRIM(E88)="",0,LEN(E88)-LEN(SUBSTITUTE(E88,",",""))+1) -> 2
A89: R-11-02 | B89: 11 | C89: Pattern Store階層: LIBRARY(Active Priority Set) | E89: F027, F029 | F89: =IF(TRIM(E89)="",0,LEN(E89)-LEN(SUBSTITUTE(E89,",",""))+1) -> 2
A90: R-11-03 | B90: 11 | C90: Pattern Store階層: CANDIDATE | D90: 検証中パターン | E90: F028 | F90: =IF(TRIM(E90)="",0,LEN(E90)-LEN(SUBSTITUTE(E90,",",""))+1) -> 1
A91: R-11-04 | B91: 11 | C91: Pattern Store階層: DEATH NOTE | D91: N回失敗即死禁止・凍結判定 | E91: F033 | F91: =IF(TRIM(E91)="",0,LEN(E91)-LEN(SUBSTITUTE(E91,",",""))+1) -> 1
A92: R-11-05 | B92: 11 | C92: Pattern Store階層: REHAB | D92: 再検証候補保管庫 | E92: F034 | F92: =IF(TRIM(E92)="",0,LEN(E92)-LEN(SUBSTITUTE(E92,",",""))+1) -> 1
A93: R-11-06 | B93: 11 | C93: 最終執行判断(再現性スコア) | D93: 類似度+件数+勝率+期待値+レジーム+執行品質+Active Priority+リスク適合 | E93: F032 | F93: =IF(TRIM(E93)="",0,LEN(E93)-LEN(SUBSTITUTE(E93,",",""))+1) -> 1
A94: R-11-07 | B94: 11 | C94: 類似件数少なすぎは参考止まり | E94: F032 | F94: =IF(TRIM(E94)="",0,LEN(E94)-LEN(SUBSTITUTE(E94,",",""))+1) -> 1
A95: R-12-01 | B95: 12 | C95: 最終目標: 全自動運用 | D95: 日本株・少数精鋭・材料重視・自動執行・自動停止 | E95: F170, F191 | F95: =IF(TRIM(E95)="",0,LEN(E95)-LEN(SUBSTITUTE(E95,",",""))+1) -> 2
A96: R-12-02 | B96: 12 | C96: 自動化する範囲 | D96: 朝分析/候補/発注/逆指値/利確/強制クローズ/異常自動停止 | E96: F170 | F96: =IF(TRIM(E96)="",0,LEN(E96)-LEN(SUBSTITUTE(E96,",",""))+1) -> 1
A97: R-12-03 | B97: 12 | C97: 自動化しない範囲 | D97: 長期現物新規買いフル自動/イレギュラー大量/異常時裁量 | E97: F113, F170 | F97: =IF(TRIM(E97)="",0,LEN(E97)-LEN(SUBSTITUTE(E97,",",""))+1) -> 2
A98: R-12-04 | B98: 12 | C98: Stage 0 Backtest | E98: F040 | F98: =IF(TRIM(E98)="",0,LEN(E98)-LEN(SUBSTITUTE(E98,",",""))+1) -> 1
A99: R-12-05 | B99: 12 | C99: Stage 1 Replay Simulation | E99: F041 | F99: =IF(TRIM(E99)="",0,LEN(E99)-LEN(SUBSTITUTE(E99,",",""))+1) -> 1
A100: R-12-06 | B100: 12 | C100: Stage 2 Paper Live | E100: F050 | F100: =IF(TRIM(E100)="",0,LEN(E100)-LEN(SUBSTITUTE(E100,",",""))+1) -> 1
A101: R-12-07 | B101: 12 | C101: Stage 3 Semi Auto | E101: F170 | F101: =IF(TRIM(E101)="",0,LEN(E101)-LEN(SUBSTITUTE(E101,",",""))+1) -> 1
A102: R-12-08 | B102: 12 | C102: Stage 4 Full Auto | E102: F170 | F102: =IF(TRIM(E102)="",0,LEN(E102)-LEN(SUBSTITUTE(E102,",",""))+1) -> 1
A103: R-12-09 | B103: 12 | C103: Stage飛ばし禁止 | E103: F190, F191, F193 | F103: =IF(TRIM(E103)="",0,LEN(E103)-LEN(SUBSTITUTE(E103,",",""))+1) -> 3
A104: R-12-10 | B104: 12 | C104: 5層防御1: signal_id冪等性 | E104: F160 | F104: =IF(TRIM(E104)="",0,LEN(E104)-LEN(SUBSTITUTE(E104,",",""))+1) -> 1
A105: R-12-11 | B105: 12 | C105: 5層防御2: 発注レート物理上限(1秒2件) | E105: F161 | F105: =IF(TRIM(E105)="",0,LEN(E105)-LEN(SUBSTITUTE(E105,",",""))+1) -> 1
A106: R-12-12 | B106: 12 | C106: 5層防御3: 同一銘柄ポジション上限1.5% | E106: F162 | F106: =IF(TRIM(E106)="",0,LEN(E106)-LEN(SUBSTITUTE(E106,",",""))+1) -> 1
A107: R-12-13 | B107: 12 | C107: 5層防御4: 異常シグナル検知(ID無/100ms未満) | E107: F163 | F107: =IF(TRIM(E107)="",0,LEN(E107)-LEN(SUBSTITUTE(E107,",",""))+1) -> 1
A108: R-12-14 | B108: 12 | C108: 5層防御5: 毎朝同意+トリプルハートビート | D108: 証券API/市場データ/ニュース3系統正常時のみ自動 | E108: F164 | F108: =IF(TRIM(E108)="",0,LEN(E108)-LEN(SUBSTITUTE(E108,",",""))+1) -> 1
A109: R-12-15 | B109: 12 | C109: Paper→Semi昇格 20営業日or50トレード | D109: 過去データ高速リプレイで短縮可 | E109: F045, F053, F190 | F109: =IF(TRIM(E109)="",0,LEN(E109)-LEN(SUBSTITUTE(E109,",",""))+1) -> 3
A110: R-12-16 | B110: 12 | C110: Paper→Semi 主戦略期待値プラス | D110: 勝率だけでなく平均損益含む | E110: F190 | F110: =IF(TRIM(E110)="",0,LEN(E110)-LEN(SUBSTITUTE(E110,",",""))+1) -> 1
A111: R-12-17 | B111: 12 | C111: Paper→Semi 最大DD想定内(-5%大幅超過なし) | E111: F190 | F111: =IF(TRIM(E111)="",0,LEN(E111)-LEN(SUBSTITUTE(E111,",",""))+1) -> 1
A112: R-12-18 | B112: 12 | C112: Paper→Semi 強制クローズ100%・緊急停止正常 | E112: F190 | F112: =IF(TRIM(E112)="",0,LEN(E112)-LEN(SUBSTITUTE(E112,",",""))+1) -> 1
...

Sheet RTM_章別サマリー
A1: 章別 要件カバレッジサマリー
A2: 要件書の各章で、要件が何件ありタスクに落ちているかを集計。未カバーが1件でもあれば要対応。
A4: 章 | B4: 章タイトル | C4: 要件数 | D4: カバー済 | E4: 未カバー | F4: カバレッジ率
A5: 1 | B5: プロジェクト概要と最重要目的 | C5: =COUNTIF(RTM_要件カバレッジ!B5:B332,A5) -> 14 | D5: =SUMPRODUCT((RTM_要件カバレッジ!B5:B332=A5)*(RTM_要件カバレッジ!F5:F332>=1)) -> 14 | E5: =C5-D5 -> 0 | F5: =IFERROR(D5/C5,0) -> 1
A6: 2 | B6: ユーザープロファイルと投資対象 | C6: =COUNTIF(RTM_要件カバレッジ!B5:B332,A6) -> 5 | D6: =SUMPRODUCT((RTM_要件カバレッジ!B5:B332=A6)*(RTM_要件カバレッジ!F5:F332>=1)) -> 4 | E6: =C6-D6 -> 1 | F6: =IFERROR(D6/C6,0) -> 0.8
A7: 3 | B7: FIREの主戦略(第一エッジ) | C7: =COUNTIF(RTM_要件カバレッジ!B5:B332,A7) -> 5 | D7: =SUMPRODUCT((RTM_要件カバレッジ!B5:B332=A7)*(RTM_要件カバレッジ!F5:F332>=1)) -> 5 | E7: =C7-D7 -> 0 | F7: =IFERROR(D7/C7,0) -> 1
A8: 4 | B8: システム構成(エージェント群) | C8: =COUNTIF(RTM_要件カバレッジ!B5:B332,A8) -> 11 | D8: =SUMPRODUCT((RTM_要件カバレッジ!B5:B332=A8)*(RTM_要件カバレッジ!F5:F332>=1)) -> 11 | E8: =C8-D8 -> 0 | F8: =IFERROR(D8/C8,0) -> 1
A9: 5 | B9: 許容損失とリスク管理(準攻撃型) | C9: =COUNTIF(RTM_要件カバレッジ!B5:B332,A9) -> 14 | D9: =SUMPRODUCT((RTM_要件カバレッジ!B5:B332=A9)*(RTM_要件カバレッジ!F5:F332>=1)) -> 14 | E9: =C9-D9 -> 0 | F9: =IFERROR(D9/C9,0) -> 1
A10: 6 | B10: LINE通知設計(注文完成形) | C10: =COUNTIF(RTM_要件カバレッジ!B5:B332,A10) -> 10 | D10: =SUMPRODUCT((RTM_要件カバレッジ!B5:B332=A10)*(RTM_要件カバレッジ!F5:F332>=1)) -> 10 | E10: =C10-D10 -> 0 | F10: =IFERROR(D10/C10,0) -> 1
A11: 7 | B11: 候補銘柄の抽出ルール | C11: =COUNTIF(RTM_要件カバレッジ!B5:B332,A11) -> 4 | D11: =SUMPRODUCT((RTM_要件カバレッジ!B5:B332=A11)*(RTM_要件カバレッジ!F5:F332>=1)) -> 4 | E11: =C11-D11 -> 0 | F11: =IFERROR(D11/C11,0) -> 1
A12: 8 | B12: 運用スケジュール(時間帯別ルール) | C12: =COUNTIF(RTM_要件カバレッジ!B5:B332,A12) -> 15 | D12: =SUMPRODUCT((RTM_要件カバレッジ!B5:B332=A12)*(RTM_要件カバレッジ!F5:F332>=1)) -> 15 | E12: =C12-D12 -> 0 | F12: =IFERROR(D12/C12,0) -> 1
A13: 10 | B13: スコアリングシステムと特徴量 | C13: =COUNTIF(RTM_要件カバレッジ!B5:B332,A13) -> 5 | D13: =SUMPRODUCT((RTM_要件カバレッジ!B5:B332=A13)*(RTM_要件カバレッジ!F5:F332>=1)) -> 5 | E13: =C13-D13 -> 0 | F13: =IFERROR(D13/C13,0) -> 1
A14: 11 | B14: Pattern Store と再現性エンジン | C14: =COUNTIF(RTM_要件カバレッジ!B5:B332,A14) -> 7 | D14: =SUMPRODUCT((RTM_要件カバレッジ!B5:B332=A14)*(RTM_要件カバレッジ!F5:F332>=1)) -> 7 | E14: =C14-D14 -> 0 | F14: =IFERROR(D14/C14,0) -> 1
A15: 12 | B15: 全自動運用モードと移行ステップ | C15: =COUNTIF(RTM_要件カバレッジ!B5:B332,A15) -> 19 | D15: =SUMPRODUCT((RTM_要件カバレッジ!B5:B332=A15)*(RTM_要件カバレッジ!F5:F332>=1)) -> 19 | E15: =C15-D15 -> 0 | F15: =IFERROR(D15/C15,0) -> 1
A16: 13 | B16: Evaluation Agent と Dashboard | C16: =COUNTIF(RTM_要件カバレッジ!B5:B332,A16) -> 19 | D16: =SUMPRODUCT((RTM_要件カバレッジ!B5:B332=A16)*(RTM_要件カバレッジ!F5:F332>=1)) -> 19 | E16: =C16-D16 -> 0 | F16: =IFERROR(D16/C16,0) -> 1
A17: 14 | B17: データソース優先順位と縮退運転 | C17: =COUNTIF(RTM_要件カバレッジ!B5:B332,A17) -> 6 | D17: =SUMPRODUCT((RTM_要件カバレッジ!B5:B332=A17)*(RTM_要件カバレッジ!F5:F332>=1)) -> 6 | E17: =C17-D17 -> 0 | F17: =IFERROR(D17/C17,0) -> 1
A18: 15 | B18: Claude Code実装に向けた次のステップ | C18: =COUNTIF(RTM_要件カバレッジ!B5:B332,A18) -> 6 | D18: =SUMPRODUCT((RTM_要件カバレッジ!B5:B332=A18)*(RTM_要件カバレッジ!F5:F332>=1)) -> 6 | E18: =C18-D18 -> 0 | F18: =IFERROR(D18/C18,0) -> 1
A19: 16 | B19: Mac miniセットアップ | C19: =COUNTIF(RTM_要件カバレッジ!B5:B332,A19) -> 10 | D19: =SUMPRODUCT((RTM_要件カバレッジ!B5:B332=A19)*(RTM_要件カバレッジ!F5:F332>=1)) -> 10 | E19: =C19-D19 -> 0 | F19: =IFERROR(D19/C19,0) -> 1
A20: 17 | B20: 執行品質設計(穴2対策) | C20: =COUNTIF(RTM_要件カバレッジ!B5:B332,A20) -> 11 | D20: =SUMPRODUCT((RTM_要件カバレッジ!B5:B332=A20)*(RTM_要件カバレッジ!F5:F332>=1)) -> 11 | E20: =C20-D20 -> 0 | F20: =IFERROR(D20/C20,0) -> 1
A21: 18 | B21: 時間軸戦略方針 | C21: =COUNTIF(RTM_要件カバレッジ!B5:B332,A21) -> 8 | D21: =SUMPRODUCT((RTM_要件カバレッジ!B5:B332=A21)*(RTM_要件カバレッジ!F5:F332>=1)) -> 8 | E21: =C21-D21 -> 0 | F21: =IFERROR(D21/C21,0) -> 1
A22: 19 | B22: Simulation / Paper Live 方針 | C22: =COUNTIF(RTM_要件カバレッジ!B5:B332,A22) -> 10 | D22: =SUMPRODUCT((RTM_要件カバレッジ!B5:B332=A22)*(RTM_要件カバレッジ!F5:F332>=1)) -> 10 | E22: =C22-D22 -> 0 | F22: =IFERROR(D22/C22,0) -> 1
A23: 20 | B23: FIREの勝率優位性の根拠 | C23: =COUNTIF(RTM_要件カバレッジ!B5:B332,A23) -> 6 | D23: =SUMPRODUCT((RTM_要件カバレッジ!B5:B332=A23)*(RTM_要件カバレッジ!F5:F332>=1)) -> 6 | E23: =C23-D23 -> 0 | F23: =IFERROR(D23/C23,0) -> 1
A24: 21 | B24: Pattern Research Agent / Pattern Store詳細 | C24: =COUNTIF(RTM_要件カバレッジ!B5:B332,A24) -> 14 | D24: =SUMPRODUCT((RTM_要件カバレッジ!B5:B332=A24)*(RTM_要件カバレッジ!F5:F332>=1)) -> 14 | E24: =C24-D24 -> 0 | F24: =IFERROR(D24/C24,0) -> 1
A25: 22 | B25: データソース依存と縮退運転設計(穴3) | C25: =COUNTIF(RTM_要件カバレッジ!B5:B332,A25) -> 10 | D25: =SUMPRODUCT((RTM_要件カバレッジ!B5:B332=A25)*(RTM_要件カバレッジ!F5:F332>=1)) -> 10 | E25: =C25-D25 -> 0 | F25: =IFERROR(D25/C25,0) -> 1
A26: 23 | B26: FIRE Runtime / 常駐基盤 | C26: =COUNTIF(RTM_要件カバレッジ!B5:B332,A26) -> 6 | D26: =SUMPRODUCT((RTM_要件カバレッジ!B5:B332=A26)*(RTM_要件カバレッジ!F5:F332>=1)) -> 6 | E26: =C26-D26 -> 0 | F26: =IFERROR(D26/C26,0) -> 1
A27: 24 | B27: 機能の絞り込みと監視階層(穴4) | C27: =COUNTIF(RTM_要件カバレッジ!B5:B332,A27) -> 8 | D27: =SUMPRODUCT((RTM_要件カバレッジ!B5:B332=A27)*(RTM_要件カバレッジ!F5:F332>=1)) -> 8 | E27: =C27-D27 -> 0 | F27: =IFERROR(D27/C27,0) -> 1
A28: 25 | B28: 戦略階層と頻度設計 | C28: =COUNTIF(RTM_要件カバレッジ!B5:B332,A28) -> 7 | D28: =SUMPRODUCT((RTM_要件カバレッジ!B5:B332=A28)*(RTM_要件カバレッジ!F5:F332>=1)) -> 7 | E28: =C28-D28 -> 0 | F28: =IFERROR(D28/C28,0) -> 1
A29: 26 | B29: FIREのエッジ定義 | C29: =COUNTIF(RTM_要件カバレッジ!B5:B332,A29) -> 9 | D29: =SUMPRODUCT((RTM_要件カバレッジ!B5:B332=A29)*(RTM_要件カバレッジ!F5:F332>=1)) -> 9 | E29: =C29-D29 -> 0 | F29: =IFERROR(D29/C29,0) -> 1
A30: 27 | B30: 目標圧力と運用規律の分離(穴5) | C30: =COUNTIF(RTM_要件カバレッジ!B5:B332,A30) -> 7 | D30: =SUMPRODUCT((RTM_要件カバレッジ!B5:B332=A30)*(RTM_要件カバレッジ!F5:F332>=1)) -> 7 | E30: =C30-D30 -> 0 | F30: =IFERROR(D30/C30,0) -> 1
A31: 28 | B31: 監督者付き自律運用システム(穴6) | C31: =COUNTIF(RTM_要件カバレッジ!B5:B332,A31) -> 9 | D31: =SUMPRODUCT((RTM_要件カバレッジ!B5:B332=A31)*(RTM_要件カバレッジ!F5:F332>=1)) -> 9 | E31: =C31-D31 -> 0 | F31: =IFERROR(D31/C31,0) -> 1
A32: 29 | B32: 成功/失敗ラベル定義(穴7) | C32: =COUNTIF(RTM_要件カバレッジ!B5:B332,A32) -> 11 | D32: =SUMPRODUCT((RTM_要件カバレッジ!B5:B332=A32)*(RTM_要件カバレッジ!F5:F332>=1)) -> 11 | E32: =C32-D32 -> 0 | F32: =IFERROR(D32/C32,0) -> 1
A33: 30 | B33: 特徴量の初期絞り込み(穴8) | C33: =COUNTIF(RTM_要件カバレッジ!B5:B332,A33) -> 2 | D33: =SUMPRODUCT((RTM_要件カバレッジ!B5:B332=A33)*(RTM_要件カバレッジ!F5:F332>=1)) -> 2 | E33: =C33-D33 -> 0 | F33: =IFERROR(D33/C33,0) -> 1
A34: 31 | B34: Pattern Storeの品質管理(穴9) | C34: =COUNTIF(RTM_要件カバレッジ!B5:B332,A34) -> 6 | D34: =SUMPRODUCT((RTM_要件カバレッジ!B5:B332=A34)*(RTM_要件カバレッジ!F5:F332>=1)) -> 6 | E34: =C34-D34 -> 0 | F34: =IFERROR(D34/C34,0) -> 1
A35: 32 | B35: 本番移行基準の厳密化(穴10) | C35: =COUNTIF(RTM_要件カバレッジ!B5:B332,A35) -> 3 | D35: =SUMPRODUCT((RTM_要件カバレッジ!B5:B332=A35)*(RTM_要件カバレッジ!F5:F332>=1)) -> 3 | E35: =C35-D35 -> 0 | F35: =IFERROR(D35/C35,0) -> 1
A36: 33 | B36: 人間の運用負荷の上限設計(穴11) | C36: =COUNTIF(RTM_要件カバレッジ!B5:B332,A36) -> 4 | D36: =SUMPRODUCT((RTM_要件カバレッジ!B5:B332=A36)*(RTM_要件カバレッジ!F5:F332>=1)) -> 4 | E36: =C36-D36 -> 0 | F36: =IFERROR(D36/C36,0) -> 1
A37: 34 | B37: 本番移行基準の詳細 | C37: =COUNTIF(RTM_要件カバレッジ!B5:B332,A37) -> 6 | D37: =SUMPRODUCT((RTM_要件カバレッジ!B5:B332=A37)*(RTM_要件カバレッジ!F5:F332>=1)) -> 6 | E37: =C37-D37 -> 0 | F37: =IFERROR(D37/C37,0) -> 1
A38: 35 | B38: Mac mini 常駐基盤時間帯別分担 | C38: =COUNTIF(RTM_要件カバレッジ!B5:B332,A38) -> 4 | D38: =SUMPRODUCT((RTM_要件カバレッジ!B5:B332=A38)*(RTM_要件カバレッジ!F5:F332>=1)) -> 4 | E38: =C38-D38 -> 0 | F38: =IFERROR(D38/C38,0) -> 1
A39: 36 | B39: 初期特徴量セットの詳細定義 | C39: =COUNTIF(RTM_要件カバレッジ!B5:B332,A39) -> 10 | D39: =SUMPRODUCT((RTM_要件カバレッジ!B5:B332=A39)*(RTM_要件カバレッジ!F5:F332>=1)) -> 10 | E39: =C39-D39 -> 0 | F39: =IFERROR(D39/C39,0) -> 1
A40: 37 | B40: Pattern Store 4階層構造 | C40: =COUNTIF(RTM_要件カバレッジ!B5:B332,A40) -> 12 | D40: =SUMPRODUCT((RTM_要件カバレッジ!B5:B332=A40)*(RTM_要件カバレッジ!F5:F332>=1)) -> 12 | E40: =C40-D40 -> 0 | F40: =IFERROR(D40/C40,0) -> 1
A41: 38 | B41: 運用モード/休止/旅行モード | C41: =COUNTIF(RTM_要件カバレッジ!B5:B332,A41) -> 10 | D41: =SUMPRODUCT((RTM_要件カバレッジ!B5:B332=A41)*(RTM_要件カバレッジ!F5:F332>=1)) -> 10 | E41: =C41-D41 -> 0 | F41: =IFERROR(D41/C41,0) -> 1
A42: 39 | B42: 運用立ち上げロードマップ | C42: =COUNTIF(RTM_要件カバレッジ!B5:B332,A42) -> 5 | D42: =SUMPRODUCT((RTM_要件カバレッジ!B5:B332=A42)*(RTM_要件カバレッジ!F5:F332>=1)) -> 5 | E42: =C42-D42 -> 0 | F42: =IFERROR(D42/C42,0) -> 1
A43: 合計 | B43: 全体 | C43: =SUM(C5:C42) -> 328 | D43: =SUM(D5:D42) -> 327 | E43: =SUM(E5:E42) -> 1 | F43: =IFERROR(D43/C43,0) -> 0.99695122
